{
"meta":{"test_sets":[],"test_metrics":[],"learn_metrics":[{"best_value":"Min","name":"RMSE"}],"launch_mode":"Train","parameters":"","iteration_count":1000,"learn_sets":["learn"],"name":"experiment"},
"iterations":[
{"learn":[0.5719695218],"iteration":0,"passed_time":0.0132854456,"remaining_time":13.27216016},
{"learn":[0.5581361912],"iteration":1,"passed_time":0.02264478452,"remaining_time":11.29974747},
{"learn":[0.5453449603],"iteration":2,"passed_time":0.0288127944,"remaining_time":9.575452007},
{"learn":[0.5330595328],"iteration":3,"passed_time":0.03591035064,"remaining_time":8.94167731},
{"learn":[0.5224192088],"iteration":4,"passed_time":0.04339327761,"remaining_time":8.635262244},
{"learn":[0.5115958925],"iteration":5,"passed_time":0.05020081434,"remaining_time":8.316601576},
{"learn":[0.5013132653],"iteration":6,"passed_time":0.05737204513,"remaining_time":8.138634402},
{"learn":[0.4913762461],"iteration":7,"passed_time":0.06420590711,"remaining_time":7.961532482},
{"learn":[0.483340676],"iteration":8,"passed_time":0.07290678348,"remaining_time":8.027846936},
{"learn":[0.4747293596],"iteration":9,"passed_time":0.07952991294,"remaining_time":7.873461381},
{"learn":[0.4673310765],"iteration":10,"passed_time":0.08605484983,"remaining_time":7.737113317},
{"learn":[0.4597236889],"iteration":11,"passed_time":0.09403970351,"remaining_time":7.742602256},
{"learn":[0.4529270359],"iteration":12,"passed_time":0.1005129839,"remaining_time":7.631255007},
{"learn":[0.4471278422],"iteration":13,"passed_time":0.1081010713,"remaining_time":7.61340402},
{"learn":[0.4413754712],"iteration":14,"passed_time":0.1149304353,"remaining_time":7.547098583},
{"learn":[0.4359594233],"iteration":15,"passed_time":0.1230426783,"remaining_time":7.567124713},
{"learn":[0.4310031449],"iteration":16,"passed_time":0.1293064309,"remaining_time":7.476954212},
{"learn":[0.4262597355],"iteration":17,"passed_time":0.1351759274,"remaining_time":7.374597814},
{"learn":[0.421845764],"iteration":18,"passed_time":0.1440422251,"remaining_time":7.437127516},
{"learn":[0.4176433547],"iteration":19,"passed_time":0.1502985982,"remaining_time":7.364631314},
{"learn":[0.4134138954],"iteration":20,"passed_time":0.1576188147,"remaining_time":7.348039027},
{"learn":[0.4098915438],"iteration":21,"passed_time":0.1646237105,"remaining_time":7.31827222},
{"learn":[0.4064118661],"iteration":22,"passed_time":0.1713441088,"remaining_time":7.278399753},
{"learn":[0.4030039863],"iteration":23,"passed_time":0.1794484803,"remaining_time":7.297571533},
{"learn":[0.3998068572],"iteration":24,"passed_time":0.1868721102,"remaining_time":7.288012299},
{"learn":[0.396581377],"iteration":25,"passed_time":0.1956230467,"remaining_time":7.328340289},
{"learn":[0.3940686804],"iteration":26,"passed_time":0.2052156783,"remaining_time":7.395365001},
{"learn":[0.3909343671],"iteration":27,"passed_time":0.2124121902,"remaining_time":7.37373746},
{"learn":[0.3880143673],"iteration":28,"passed_time":0.2193731001,"remaining_time":7.34521656},
{"learn":[0.3858483461],"iteration":29,"passed_time":0.2276000618,"remaining_time":7.359068664},
{"learn":[0.383078214],"iteration":30,"passed_time":0.2354097752,"remaining_time":7.358453942},
{"learn":[0.3811198482],"iteration":31,"passed_time":0.2433071492,"remaining_time":7.360041263},
{"learn":[0.3791599006],"iteration":32,"passed_time":0.2500408507,"remaining_time":7.326954625},
{"learn":[0.3770756441],"iteration":33,"passed_time":0.2573842298,"remaining_time":7.312740175},
{"learn":[0.375420358],"iteration":34,"passed_time":0.2638261246,"remaining_time":7.274063151},
{"learn":[0.3736517401],"iteration":35,"passed_time":0.2708091028,"remaining_time":7.251665975},
{"learn":[0.3723045647],"iteration":36,"passed_time":0.2776993301,"remaining_time":7.227687971},
{"learn":[0.3706354053],"iteration":37,"passed_time":0.2845677904,"remaining_time":7.204058274},
{"learn":[0.368855578],"iteration":38,"passed_time":0.2928161577,"remaining_time":7.215290449},
{"learn":[0.3672563303],"iteration":39,"passed_time":0.2985569595,"remaining_time":7.165367029},
{"learn":[0.3656051645],"iteration":40,"passed_time":0.3060941635,"remaining_time":7.159617142},
{"learn":[0.3640304333],"iteration":41,"passed_time":0.3127560981,"remaining_time":7.133817667},
{"learn":[0.3627301158],"iteration":42,"passed_time":0.3196940262,"remaining_time":7.115050768},
{"learn":[0.3616052594],"iteration":43,"passed_time":0.326774213,"remaining_time":7.099912445},
{"learn":[0.3603382113],"iteration":44,"passed_time":0.3330892908,"remaining_time":7.06889495},
{"learn":[0.3592479221],"iteration":45,"passed_time":0.3395978523,"remaining_time":7.042964153},
{"learn":[0.3579399921],"iteration":46,"passed_time":0.346656272,"remaining_time":7.02900909},
{"learn":[0.3568727125],"iteration":47,"passed_time":0.3551671889,"remaining_time":7.044149247},
{"learn":[0.3559806932],"iteration":48,"passed_time":0.3619064326,"remaining_time":7.023939131},
{"learn":[0.3548001683],"iteration":49,"passed_time":0.3685250039,"remaining_time":7.001975073},
{"learn":[0.3539150265],"iteration":50,"passed_time":0.3768348971,"remaining_time":7.012084653},
{"learn":[0.3530716169],"iteration":51,"passed_time":0.3832535591,"remaining_time":6.987007192},
{"learn":[0.3522041656],"iteration":52,"passed_time":0.3913629707,"remaining_time":6.992844024},
{"learn":[0.351436406],"iteration":53,"passed_time":0.3978395141,"remaining_time":6.969558896},
{"learn":[0.3506465933],"iteration":54,"passed_time":0.4050296505,"remaining_time":6.959145813},
{"learn":[0.3498505782],"iteration":55,"passed_time":0.4118902394,"remaining_time":6.943292606},
{"learn":[0.3488941497],"iteration":56,"passed_time":0.4196684167,"remaining_time":6.942935386},
{"learn":[0.3481627801],"iteration":57,"passed_time":0.4268265652,"remaining_time":6.932252146},
{"learn":[0.3474969216],"iteration":58,"passed_time":0.4334037912,"remaining_time":6.912423178},
{"learn":[0.3468533362],"iteration":59,"passed_time":0.4413495084,"remaining_time":6.914475631},
{"learn":[0.3459584145],"iteration":60,"passed_time":0.4484779079,"remaining_time":6.903618943},
{"learn":[0.3452173496],"iteration":61,"passed_time":0.4554150629,"remaining_time":6.889989177},
{"learn":[0.3446020223],"iteration":62,"passed_time":0.4623790551,"remaining_time":6.876971026},
{"learn":[0.3437726708],"iteration":63,"passed_time":0.4695112599,"remaining_time":6.866602176},
{"learn":[0.3430539136],"iteration":64,"passed_time":0.4765237962,"remaining_time":6.85461153},
{"learn":[0.3424008263],"iteration":65,"passed_time":0.4830354098,"remaining_time":6.835682921},
{"learn":[0.3416735086],"iteration":66,"passed_time":0.490321279,"remaining_time":6.827906765},
{"learn":[0.3411503751],"iteration":67,"passed_time":0.4971278318,"remaining_time":6.813575577},
{"learn":[0.340620724],"iteration":68,"passed_time":0.504844443,"remaining_time":6.811741687},
{"learn":[0.3402049799],"iteration":69,"passed_time":0.5110553946,"remaining_time":6.789735956},
{"learn":[0.3395109721],"iteration":70,"passed_time":0.5179313147,"remaining_time":6.776875935},
{"learn":[0.3390724268],"iteration":71,"passed_time":0.5249896542,"remaining_time":6.76653332},
{"learn":[0.3384996549],"iteration":72,"passed_time":0.5316654944,"remaining_time":6.751423469},
{"learn":[0.3380316046],"iteration":73,"passed_time":0.5391442848,"remaining_time":6.746589293},
{"learn":[0.3374744484],"iteration":74,"passed_time":0.5459013698,"remaining_time":6.732783561},
{"learn":[0.3369383556],"iteration":75,"passed_time":0.5538604505,"remaining_time":6.733777055},
{"learn":[0.336366789],"iteration":76,"passed_time":0.5600271652,"remaining_time":6.713052902},
{"learn":[0.3358742088],"iteration":77,"passed_time":0.5669589486,"remaining_time":6.701745521},
{"learn":[0.3352839514],"iteration":78,"passed_time":0.573760652,"remaining_time":6.689032412},
{"learn":[0.3346917034],"iteration":79,"passed_time":0.5807338109,"remaining_time":6.678438826},
{"learn":[0.33421769],"iteration":80,"passed_time":0.5875549621,"remaining_time":6.666210002},
{"learn":[0.3336706837],"iteration":81,"passed_time":0.5943406816,"remaining_time":6.653716411},
{"learn":[0.3332113103],"iteration":82,"passed_time":0.602447272,"remaining_time":6.655953595},
{"learn":[0.3328290362],"iteration":83,"passed_time":0.608904448,"remaining_time":6.639958028},
{"learn":[0.3322322514],"iteration":84,"passed_time":0.6153319553,"remaining_time":6.623867519},
{"learn":[0.3318029497],"iteration":85,"passed_time":0.6234110257,"remaining_time":6.625554389},
{"learn":[0.3314235048],"iteration":86,"passed_time":0.6301466951,"remaining_time":6.612918766},
{"learn":[0.3309258527],"iteration":87,"passed_time":0.6376763991,"remaining_time":6.608646318},
{"learn":[0.3305151092],"iteration":88,"passed_time":0.6440838965,"remaining_time":6.592813817},
{"learn":[0.3301668869],"iteration":89,"passed_time":0.6524675044,"remaining_time":6.597171433},
{"learn":[0.3298811818],"iteration":90,"passed_time":0.6590647303,"remaining_time":6.583404833},
{"learn":[0.3295424727],"iteration":91,"passed_time":0.6655348781,"remaining_time":6.568539884},
{"learn":[0.3292134976],"iteration":92,"passed_time":0.6744316778,"remaining_time":6.577521847},
{"learn":[0.3287919022],"iteration":93,"passed_time":0.6811034819,"remaining_time":6.56467824},
{"learn":[0.3284510097],"iteration":94,"passed_time":0.689158978,"remaining_time":6.565146053},
{"learn":[0.3281937717],"iteration":95,"passed_time":0.6958077299,"remaining_time":6.552189456},
{"learn":[0.3277332513],"iteration":96,"passed_time":0.7026922042,"remaining_time":6.541557324},
{"learn":[0.3274403151],"iteration":97,"passed_time":0.7095506946,"remaining_time":6.530762516},
{"learn":[0.3271894153],"iteration":98,"passed_time":0.7163890747,"remaining_time":6.519864205},
{"learn":[0.3267487371],"iteration":99,"passed_time":0.7237698834,"remaining_time":6.51392895},
{"learn":[0.3263729997],"iteration":100,"passed_time":0.7301362061,"remaining_time":6.498935142},
{"learn":[0.3260076659],"iteration":101,"passed_time":0.7374394949,"remaining_time":6.492359475},
{"learn":[0.325734604],"iteration":102,"passed_time":0.7439342511,"remaining_time":6.478728381},
{"learn":[0.3253111454],"iteration":103,"passed_time":0.7512826402,"remaining_time":6.4725889},
{"learn":[0.3250625013],"iteration":104,"passed_time":0.7575785012,"remaining_time":6.457454844},
{"learn":[0.3248430684],"iteration":105,"passed_time":0.7638031074,"remaining_time":6.441886585},
{"learn":[0.3245363844],"iteration":106,"passed_time":0.7713371688,"remaining_time":6.437421418},
{"learn":[0.3241197582],"iteration":107,"passed_time":0.7779554087,"remaining_time":6.425335413},
{"learn":[0.323727228],"iteration":108,"passed_time":0.7848970516,"remaining_time":6.41599333},
{"learn":[0.3234768849],"iteration":109,"passed_time":0.7918952607,"remaining_time":6.407152564},
{"learn":[0.3232253296],"iteration":110,"passed_time":0.7984372457,"remaining_time":6.394691094},
{"learn":[0.3226205087],"iteration":111,"passed_time":0.8060816483,"remaining_time":6.391075925},
{"learn":[0.3224406487],"iteration":112,"passed_time":0.8128134221,"remaining_time":6.380225711},
{"learn":[0.3221355917],"iteration":113,"passed_time":0.8204175637,"remaining_time":6.376227732},
{"learn":[0.3218463386],"iteration":114,"passed_time":0.8270956127,"remaining_time":6.36504015},
{"learn":[0.3216667873],"iteration":115,"passed_time":0.8344174557,"remaining_time":6.358836472},
{"learn":[0.321404793],"iteration":116,"passed_time":0.8409366094,"remaining_time":6.346555779},
{"learn":[0.321182511],"iteration":117,"passed_time":0.8480636034,"remaining_time":6.338916086},
{"learn":[0.3207704646],"iteration":118,"passed_time":0.8545585503,"remaining_time":6.326605738},
{"learn":[0.3204671347],"iteration":119,"passed_time":0.8609627043,"remaining_time":6.313726498},
{"learn":[0.3200547225],"iteration":120,"passed_time":0.8678691264,"remaining_time":6.304602993},
{"learn":[0.319855934],"iteration":121,"passed_time":0.8746186813,"remaining_time":6.294386903},
{"learn":[0.3196013036],"iteration":122,"passed_time":0.881381168,"remaining_time":6.284319385},
{"learn":[0.3192725212],"iteration":123,"passed_time":0.8883539353,"remaining_time":6.275790704},
{"learn":[0.3187705439],"iteration":124,"passed_time":0.8948578481,"remaining_time":6.264004937},
{"learn":[0.3184579283],"iteration":125,"passed_time":0.9016705154,"remaining_time":6.254444686},
{"learn":[0.3180699163],"iteration":126,"passed_time":0.9083858836,"remaining_time":6.244258869},
{"learn":[0.3178448794],"iteration":127,"passed_time":0.9156548853,"remaining_time":6.237898906},
{"learn":[0.3175015187],"iteration":128,"passed_time":0.9221204749,"remaining_time":6.226100261},
{"learn":[0.3173372245],"iteration":129,"passed_time":0.9287544678,"remaining_time":6.215510669},
{"learn":[0.3170076093],"iteration":130,"passed_time":0.9366260787,"remaining_time":6.213191316},
{"learn":[0.3166980082],"iteration":131,"passed_time":0.9436302918,"remaining_time":6.20508404},
{"learn":[0.3163676001],"iteration":132,"passed_time":0.9503563427,"remaining_time":6.195180069},
{"learn":[0.3161497557],"iteration":133,"passed_time":0.9572104557,"remaining_time":6.186151154},
{"learn":[0.3159368247],"iteration":134,"passed_time":0.964133936,"remaining_time":6.177598923},
{"learn":[0.3155718374],"iteration":135,"passed_time":0.9717391217,"remaining_time":6.173401479},
{"learn":[0.3154673707],"iteration":136,"passed_time":0.981924965,"remaining_time":6.185410546},
{"learn":[0.3152157097],"iteration":137,"passed_time":0.9912213824,"remaining_time":6.191542258},
{"learn":[0.3148597742],"iteration":138,"passed_time":0.999150433,"remaining_time":6.188982178},
{"learn":[0.3145895565],"iteration":139,"passed_time":1.005381033,"remaining_time":6.17591206},
{"learn":[0.3143130429],"iteration":140,"passed_time":1.011777185,"remaining_time":6.163947532},
{"learn":[0.3140025194],"iteration":141,"passed_time":1.019620563,"remaining_time":6.160805938},
{"learn":[0.3138212346],"iteration":142,"passed_time":1.026438813,"remaining_time":6.151454982},
{"learn":[0.31351488],"iteration":143,"passed_time":1.034166438,"remaining_time":6.147544937},
{"learn":[0.3131842565],"iteration":144,"passed_time":1.040208273,"remaining_time":6.133641888},
{"learn":[0.3128900787],"iteration":145,"passed_time":1.047105087,"remaining_time":6.124847564},
{"learn":[0.3125771942],"iteration":146,"passed_time":1.054321127,"remaining_time":6.117931438},
{"learn":[0.3123202974],"iteration":147,"passed_time":1.06083011,"remaining_time":6.106940904},
{"learn":[0.3121167366],"iteration":148,"passed_time":1.068542916,"remaining_time":6.102886051},
{"learn":[0.3117548482],"iteration":149,"passed_time":1.074845725,"remaining_time":6.090792442},
{"learn":[0.3114562079],"iteration":150,"passed_time":1.082347798,"remaining_time":6.085518417},
{"learn":[0.3110141049],"iteration":151,"passed_time":1.089139331,"remaining_time":6.076251006},
{"learn":[0.310847616],"iteration":152,"passed_time":1.096921966,"remaining_time":6.072502651},
{"learn":[0.3106721305],"iteration":153,"passed_time":1.10389618,"remaining_time":6.064260831},
{"learn":[0.3104410565],"iteration":154,"passed_time":1.110342934,"remaining_time":6.053159865},
{"learn":[0.3102256033],"iteration":155,"passed_time":1.11800817,"remaining_time":6.048710867},
{"learn":[0.3100790637],"iteration":156,"passed_time":1.124431822,"remaining_time":6.037554304},
{"learn":[0.3098752297],"iteration":157,"passed_time":1.132470892,"remaining_time":6.0350664},
{"learn":[0.3095789595],"iteration":158,"passed_time":1.138649655,"remaining_time":6.02266893},
{"learn":[0.3093930155],"iteration":159,"passed_time":1.145759781,"remaining_time":6.015238853},
{"learn":[0.3091239305],"iteration":160,"passed_time":1.153572437,"remaining_time":6.011473754},
{"learn":[0.3089027303],"iteration":161,"passed_time":1.160104472,"remaining_time":6.001034244},
{"learn":[0.3085815735],"iteration":162,"passed_time":1.168176725,"remaining_time":5.99855165},
{"learn":[0.3082546634],"iteration":163,"passed_time":1.175065446,"remaining_time":5.989967763},
{"learn":[0.3080101589],"iteration":164,"passed_time":1.181533245,"remaining_time":5.9792743},
{"learn":[0.3075551934],"iteration":165,"passed_time":1.189111704,"remaining_time":5.974211813},
{"learn":[0.307278049],"iteration":166,"passed_time":1.197431878,"remaining_time":5.972818889},
{"learn":[0.3070282197],"iteration":167,"passed_time":1.204879765,"remaining_time":5.967023598},
{"learn":[0.3067662686],"iteration":168,"passed_time":1.211205395,"remaining_time":5.955690433},
{"learn":[0.3064600148],"iteration":169,"passed_time":1.220287556,"remaining_time":5.957874537},
{"learn":[0.3062353687],"iteration":170,"passed_time":1.226864129,"remaining_time":5.9477799},
{"learn":[0.3058619179],"iteration":171,"passed_time":1.234925529,"remaining_time":5.944874057},
{"learn":[0.3056106284],"iteration":172,"passed_time":1.241519723,"remaining_time":5.934894859},
{"learn":[0.3049836382],"iteration":173,"passed_time":1.249526273,"remaining_time":5.931659204},
{"learn":[0.3046972916],"iteration":174,"passed_time":1.256660998,"remaining_time":5.92425899},
{"learn":[0.3044756631],"iteration":175,"passed_time":1.262705815,"remaining_time":5.911759044},
{"learn":[0.3041805535],"iteration":176,"passed_time":1.26939787,"remaining_time":5.902341509},
{"learn":[0.3039145846],"iteration":177,"passed_time":1.275917385,"remaining_time":5.892157814},
{"learn":[0.3036088631],"iteration":178,"passed_time":1.283527852,"remaining_time":5.887018809},
{"learn":[0.3033256678],"iteration":179,"passed_time":1.29038324,"remaining_time":5.878412539},
{"learn":[0.3030226852],"iteration":180,"passed_time":1.297562423,"remaining_time":5.871290742},
{"learn":[0.3028841866],"iteration":181,"passed_time":1.304432359,"remaining_time":5.862778405},
{"learn":[0.3024813747],"iteration":182,"passed_time":1.310571805,"remaining_time":5.851022757},
{"learn":[0.3022181684],"iteration":183,"passed_time":1.318036649,"remaining_time":5.845206011},
{"learn":[0.3019287023],"iteration":184,"passed_time":1.32396967,"remaining_time":5.83262314},
{"learn":[0.3015613443],"iteration":185,"passed_time":1.330971283,"remaining_time":5.824788301},
{"learn":[0.3014730489],"iteration":186,"passed_time":1.337836088,"remaining_time":5.816367592},
{"learn":[0.3011707771],"iteration":187,"passed_time":1.344766486,"remaining_time":5.808246738},
{"learn":[0.30083107],"iteration":188,"passed_time":1.351869384,"remaining_time":5.800878678},
{"learn":[0.3005015849],"iteration":189,"passed_time":1.358437232,"remaining_time":5.791232411},
{"learn":[0.3002887051],"iteration":190,"passed_time":1.366149536,"remaining_time":5.786465837},
{"learn":[0.3000288212],"iteration":191,"passed_time":1.373048037,"remaining_time":5.778243821},
{"learn":[0.2998488716],"iteration":192,"passed_time":1.38015245,"remaining_time":5.770896515},
{"learn":[0.2996070981],"iteration":193,"passed_time":1.387084123,"remaining_time":5.762834038},
{"learn":[0.2993398937],"iteration":194,"passed_time":1.393635165,"remaining_time":5.753211833},
{"learn":[0.2991354758],"iteration":195,"passed_time":1.400715351,"remaining_time":5.745791543},
{"learn":[0.2988744025],"iteration":196,"passed_time":1.406964817,"remaining_time":5.734988568},
{"learn":[0.2986135343],"iteration":197,"passed_time":1.413892614,"remaining_time":5.726979176},
{"learn":[0.2983173481],"iteration":198,"passed_time":1.42064478,"remaining_time":5.718273712},
{"learn":[0.2980989334],"iteration":199,"passed_time":1.427454184,"remaining_time":5.709816736},
{"learn":[0.2979744201],"iteration":200,"passed_time":1.43458926,"remaining_time":5.702670741},
{"learn":[0.2975422091],"iteration":201,"passed_time":1.441343454,"remaining_time":5.694020179},
{"learn":[0.2970912785],"iteration":202,"passed_time":1.447841252,"remaining_time":5.684381665},
{"learn":[0.2967943005],"iteration":203,"passed_time":1.453985848,"remaining_time":5.673395761},
{"learn":[0.2966438755],"iteration":204,"passed_time":1.462750962,"remaining_time":5.672619583},
{"learn":[0.2964337772],"iteration":205,"passed_time":1.469158901,"remaining_time":5.662680423},
{"learn":[0.2961754338],"iteration":206,"passed_time":1.475362824,"remaining_time":5.651993814},
{"learn":[0.2960349598],"iteration":207,"passed_time":1.482568101,"remaining_time":5.645163154},
{"learn":[0.2958524706],"iteration":208,"passed_time":1.488699595,"remaining_time":5.634264974},
{"learn":[0.2956347378],"iteration":209,"passed_time":1.49626459,"remaining_time":5.628804886},
{"learn":[0.2953976589],"iteration":210,"passed_time":1.502883272,"remaining_time":5.619786263},
{"learn":[0.2953497566],"iteration":211,"passed_time":1.509206834,"remaining_time":5.609693325},
{"learn":[0.295094308],"iteration":212,"passed_time":1.516727331,"remaining_time":5.604058259},
{"learn":[0.294943639],"iteration":213,"passed_time":1.523713492,"remaining_time":5.596443011},
{"learn":[0.2946838834],"iteration":214,"passed_time":1.531041459,"remaining_time":5.590081606},
{"learn":[0.2943222448],"iteration":215,"passed_time":1.537541657,"remaining_time":5.580706755},
{"learn":[0.2941669319],"iteration":216,"passed_time":1.545561912,"remaining_time":5.576843213},
{"learn":[0.2940250124],"iteration":217,"passed_time":1.551940273,"remaining_time":5.567051805},
{"learn":[0.2938818456],"iteration":218,"passed_time":1.558252821,"remaining_time":5.557056863},
{"learn":[0.2933336433],"iteration":219,"passed_time":1.565928167,"remaining_time":5.551927138},
{"learn":[0.2931632217],"iteration":220,"passed_time":1.571973557,"remaining_time":5.541028962},
{"learn":[0.2929050766],"iteration":221,"passed_time":1.579645007,"remaining_time":5.535873044},
{"learn":[0.2925357623],"iteration":222,"passed_time":1.586145476,"remaining_time":5.526614508},
{"learn":[0.2923134986],"iteration":223,"passed_time":1.593005905,"remaining_time":5.518627598},
{"learn":[0.2919228334],"iteration":224,"passed_time":1.599018242,"remaining_time":5.507729501},
{"learn":[0.2917505449],"iteration":225,"passed_time":1.60564607,"remaining_time":5.49898256},
{"learn":[0.2916977571],"iteration":226,"passed_time":1.612340354,"remaining_time":5.49048059},
{"learn":[0.2914365379],"iteration":227,"passed_time":1.618915763,"remaining_time":5.48159197},
{"learn":[0.2910369104],"iteration":228,"passed_time":1.625262317,"remaining_time":5.47195304},
{"learn":[0.2907949747],"iteration":229,"passed_time":1.63274172,"remaining_time":5.466135322},
{"learn":[0.2905689593],"iteration":230,"passed_time":1.638830653,"remaining_time":5.45567434},
{"learn":[0.2901307098],"iteration":231,"passed_time":1.646899413,"remaining_time":5.451804952},
{"learn":[0.2900229073],"iteration":232,"passed_time":1.652724311,"remaining_time":5.440513074},
{"learn":[0.2897983722],"iteration":233,"passed_time":1.659417048,"remaining_time":5.432108799},
{"learn":[0.2894504965],"iteration":234,"passed_time":1.666294987,"remaining_time":5.424321978},
{"learn":[0.2891684973],"iteration":235,"passed_time":1.67275655,"remaining_time":5.415194933},
{"learn":[0.2889441355],"iteration":236,"passed_time":1.680328563,"remaining_time":5.409665375},
{"learn":[0.2886605582],"iteration":237,"passed_time":1.687010448,"remaining_time":5.401268744},
{"learn":[0.2883932433],"iteration":238,"passed_time":1.69516997,"remaining_time":5.39759141},
{"learn":[0.2881637611],"iteration":239,"passed_time":1.701599154,"remaining_time":5.38839732},
{"learn":[0.2881269298],"iteration":240,"passed_time":1.707878489,"remaining_time":5.378754244},
{"learn":[0.2880189687],"iteration":241,"passed_time":1.714902872,"remaining_time":5.371472633},
{"learn":[0.287794867],"iteration":242,"passed_time":1.721182237,"remaining_time":5.361872238},
{"learn":[0.2876760991],"iteration":243,"passed_time":1.728099382,"remaining_time":5.354275136},
{"learn":[0.2875150876],"iteration":244,"passed_time":1.734127262,"remaining_time":5.343943195},
{"learn":[0.2873081919],"iteration":245,"passed_time":1.740637771,"remaining_time":5.335125527},
{"learn":[0.2872662466],"iteration":246,"passed_time":1.747894424,"remaining_time":5.328601218},
{"learn":[0.2871174218],"iteration":247,"passed_time":1.754221279,"remaining_time":5.319251619},
{"learn":[0.2869819024],"iteration":248,"passed_time":1.760590081,"remaining_time":5.310052815},
{"learn":[0.286729232],"iteration":249,"passed_time":1.767402809,"remaining_time":5.302208426},
{"learn":[0.2863939511],"iteration":250,"passed_time":1.773945376,"remaining_time":5.293566082},
{"learn":[0.2863617105],"iteration":251,"passed_time":1.780677481,"remaining_time":5.285503},
{"learn":[0.2860231565],"iteration":252,"passed_time":1.787488683,"remaining_time":5.277683976},
{"learn":[0.2857010864],"iteration":253,"passed_time":1.795821166,"remaining_time":5.274340905},
{"learn":[0.285667331],"iteration":254,"passed_time":1.801775231,"remaining_time":5.264009988},
{"learn":[0.2856176548],"iteration":255,"passed_time":1.808203541,"remaining_time":5.255091542},
{"learn":[0.285458202],"iteration":256,"passed_time":1.81546186,"remaining_time":5.24859207},
{"learn":[0.2853206729],"iteration":257,"passed_time":1.821846034,"remaining_time":5.239572703},
{"learn":[0.28497788],"iteration":258,"passed_time":1.829342977,"remaining_time":5.233757321},
{"learn":[0.284832532],"iteration":259,"passed_time":1.835951368,"remaining_time":5.225400047},
{"learn":[0.2846690603],"iteration":260,"passed_time":1.844041834,"remaining_time":5.221252548},
{"learn":[0.2846042116],"iteration":261,"passed_time":1.850867041,"remaining_time":5.213510978},
{"learn":[0.2843584318],"iteration":262,"passed_time":1.857489367,"remaining_time":5.205207847},
{"learn":[0.2840131556],"iteration":263,"passed_time":1.86437836,"remaining_time":5.197660882},
{"learn":[0.2839660561],"iteration":264,"passed_time":1.870437454,"remaining_time":5.18781709},
{"learn":[0.283784895],"iteration":265,"passed_time":1.877476065,"remaining_time":5.18070463},
{"learn":[0.2836229198],"iteration":266,"passed_time":1.883531535,"remaining_time":5.170893689},
{"learn":[0.2834204681],"iteration":267,"passed_time":1.889896643,"remaining_time":5.161956502},
{"learn":[0.2833842575],"iteration":268,"passed_time":1.896265255,"remaining_time":5.153047959},
{"learn":[0.2831408597],"iteration":269,"passed_time":1.902714951,"remaining_time":5.144377459},
{"learn":[0.2829793864],"iteration":270,"passed_time":1.910557054,"remaining_time":5.139468974},
{"learn":[0.2829411447],"iteration":271,"passed_time":1.915790517,"remaining_time":5.127556972},
{"learn":[0.2825788217],"iteration":272,"passed_time":1.922412512,"remaining_time":5.119391561},
{"learn":[0.2824178137],"iteration":273,"passed_time":1.929564124,"remaining_time":5.112640709},
{"learn":[0.2823836278],"iteration":274,"passed_time":1.935857947,"remaining_time":5.103625497},
{"learn":[0.2821802068],"iteration":275,"passed_time":1.944036405,"remaining_time":5.099573758},
{"learn":[0.2819633073],"iteration":276,"passed_time":1.950593219,"remaining_time":5.091259558},
{"learn":[0.2817058267],"iteration":277,"passed_time":1.957731006,"remaining_time":5.084466858},
{"learn":[0.2815691216],"iteration":278,"passed_time":1.964760752,"remaining_time":5.07739248},
{"learn":[0.2813790619],"iteration":279,"passed_time":1.971230357,"remaining_time":5.068878061},
{"learn":[0.2811830209],"iteration":280,"passed_time":1.97913245,"remaining_time":5.064043529},
{"learn":[0.2811546259],"iteration":281,"passed_time":1.98528041,"remaining_time":5.054721043},
{"learn":[0.2811207825],"iteration":282,"passed_time":1.992852061,"remaining_time":5.049028014},
{"learn":[0.2809714069],"iteration":283,"passed_time":1.999308545,"remaining_time":5.040510275},
{"learn":[0.2808301895],"iteration":284,"passed_time":2.005964224,"remaining_time":5.032506738},
{"learn":[0.2806091369],"iteration":285,"passed_time":2.013006359,"remaining_time":5.025477414},
{"learn":[0.2804854123],"iteration":286,"passed_time":2.019073867,"remaining_time":5.016026715},
{"learn":[0.280386552],"iteration":287,"passed_time":2.026949012,"remaining_time":5.011068391},
{"learn":[0.2801931557],"iteration":288,"passed_time":2.033261239,"remaining_time":5.002244777},
{"learn":[0.2799500459],"iteration":289,"passed_time":2.041291674,"remaining_time":4.997645134},
{"learn":[0.2796740935],"iteration":290,"passed_time":2.04790384,"remaining_time":4.989566401},
{"learn":[0.2796507409],"iteration":291,"passed_time":2.054244972,"remaining_time":4.980840549},
{"learn":[0.2794117948],"iteration":292,"passed_time":2.061577156,"remaining_time":4.974522354},
{"learn":[0.2791601361],"iteration":293,"passed_time":2.0683738,"remaining_time":4.966911233},
{"learn":[0.2788983284],"iteration":294,"passed_time":2.076171997,"remaining_time":4.961699179},
{"learn":[0.2786806102],"iteration":295,"passed_time":2.082444796,"remaining_time":4.952841677},
{"learn":[0.2784639949],"iteration":296,"passed_time":2.089122995,"remaining_time":4.944961164},
{"learn":[0.278139242],"iteration":297,"passed_time":2.095999076,"remaining_time":4.937554871},
{"learn":[0.2780203318],"iteration":298,"passed_time":2.102302899,"remaining_time":4.928810476},
{"learn":[0.2778800789],"iteration":299,"passed_time":2.109426459,"remaining_time":4.921995072},
{"learn":[0.2777587495],"iteration":300,"passed_time":2.115791196,"remaining_time":4.913415435},
{"learn":[0.2775003975],"iteration":301,"passed_time":2.123783389,"remaining_time":4.908611938},
{"learn":[0.2771966758],"iteration":302,"passed_time":2.129963507,"remaining_time":4.899619024},
{"learn":[0.2771719633],"iteration":303,"passed_time":2.13666509,"remaining_time":4.891838496},
{"learn":[0.2769935276],"iteration":304,"passed_time":2.143694122,"remaining_time":4.884811197},
{"learn":[0.2768456843],"iteration":305,"passed_time":2.149922745,"remaining_time":4.875968578},
{"learn":[0.2765916623],"iteration":306,"passed_time":2.158113923,"remaining_time":4.871573123},
{"learn":[0.276337627],"iteration":307,"passed_time":2.164564764,"remaining_time":4.863242911},
{"learn":[0.2763176169],"iteration":308,"passed_time":2.170592784,"remaining_time":4.853979333},
{"learn":[0.2760399162],"iteration":309,"passed_time":2.178631252,"remaining_time":4.849211497},
{"learn":[0.2758811696],"iteration":310,"passed_time":2.185865455,"remaining_time":4.84264083},
{"learn":[0.2757242971],"iteration":311,"passed_time":2.192872479,"remaining_time":4.835564954},
{"learn":[0.2755467238],"iteration":312,"passed_time":2.198739044,"remaining_time":4.825986335},
{"learn":[0.2753499757],"iteration":313,"passed_time":2.205689823,"remaining_time":4.818800059},
{"learn":[0.2751215417],"iteration":314,"passed_time":2.213251615,"remaining_time":4.812943989},
{"learn":[0.2748161093],"iteration":315,"passed_time":2.219536703,"remaining_time":4.804313624},
{"learn":[0.2747062164],"iteration":316,"passed_time":2.227106066,"remaining_time":4.79846512},
{"learn":[0.2745996647],"iteration":317,"passed_time":2.233815621,"remaining_time":4.790761803},
{"learn":[0.2744012444],"iteration":318,"passed_time":2.240915446,"remaining_time":4.783897865},
{"learn":[0.2741245012],"iteration":319,"passed_time":2.247198175,"remaining_time":4.775296121},
{"learn":[0.2739480359],"iteration":320,"passed_time":2.25311993,"remaining_time":4.765945273},
{"learn":[0.2736802218],"iteration":321,"passed_time":2.26053357,"remaining_time":4.75975702},
{"learn":[0.2734152778],"iteration":322,"passed_time":2.266920907,"remaining_time":4.751410074},
{"learn":[0.2733171545],"iteration":323,"passed_time":2.273689257,"remaining_time":4.743870178},
{"learn":[0.2731850309],"iteration":324,"passed_time":2.280531974,"remaining_time":4.736489485},
{"learn":[0.273170777],"iteration":325,"passed_time":2.286381069,"remaining_time":4.727057793},
{"learn":[0.2729544577],"iteration":326,"passed_time":2.294428101,"remaining_time":4.722171597},
{"learn":[0.2727459708],"iteration":327,"passed_time":2.300908591,"remaining_time":4.714056625},
{"learn":[0.2725727648],"iteration":328,"passed_time":2.308538415,"remaining_time":4.708295673},
{"learn":[0.2723940624],"iteration":329,"passed_time":2.31521539,"remaining_time":4.700588821},
{"learn":[0.2721861722],"iteration":330,"passed_time":2.32353466,"remaining_time":4.696207516},
{"learn":[0.2720412257],"iteration":331,"passed_time":2.330613793,"remaining_time":4.68930727},
{"learn":[0.2717856756],"iteration":332,"passed_time":2.337695285,"remaining_time":4.682410676},
{"learn":[0.2715230565],"iteration":333,"passed_time":2.344374569,"remaining_time":4.674710967},
{"learn":[0.2712556861],"iteration":334,"passed_time":2.351026654,"remaining_time":4.666963358},
{"learn":[0.2710074521],"iteration":335,"passed_time":2.358653346,"remaining_time":4.661148279},
{"learn":[0.2708421844],"iteration":336,"passed_time":2.365459397,"remaining_time":4.653707952},
{"learn":[0.2706194646],"iteration":337,"passed_time":2.372379744,"remaining_time":4.646495239},
{"learn":[0.2703775677],"iteration":338,"passed_time":2.378756459,"remaining_time":4.638224245},
{"learn":[0.2702104067],"iteration":339,"passed_time":2.385036687,"remaining_time":4.629777099},
{"learn":[0.2700077035],"iteration":340,"passed_time":2.392474735,"remaining_time":4.623580206},
{"learn":[0.2699330719],"iteration":341,"passed_time":2.398965907,"remaining_time":4.615554288},
{"learn":[0.2697908406],"iteration":342,"passed_time":2.40604019,"remaining_time":4.608654241},
{"learn":[0.269393603],"iteration":343,"passed_time":2.412453159,"remaining_time":4.600492071},
{"learn":[0.2691583657],"iteration":344,"passed_time":2.419383447,"remaining_time":4.593322196},
{"learn":[0.2691229619],"iteration":345,"passed_time":2.426048765,"remaining_time":4.585652867},
{"learn":[0.2688960158],"iteration":346,"passed_time":2.432287497,"remaining_time":4.577186558},
{"learn":[0.2686091359],"iteration":347,"passed_time":2.440572903,"remaining_time":4.572567622},
{"learn":[0.2685733077],"iteration":348,"passed_time":2.446260381,"remaining_time":4.563081685},
{"learn":[0.268399581],"iteration":349,"passed_time":2.453248098,"remaining_time":4.556032183},
{"learn":[0.2680571311],"iteration":350,"passed_time":2.460323396,"remaining_time":4.549144968},
{"learn":[0.2676979763],"iteration":351,"passed_time":2.466503895,"remaining_time":4.540609444},
{"learn":[0.267555796],"iteration":352,"passed_time":2.473889604,"remaining_time":4.534296243},
{"learn":[0.2674844103],"iteration":353,"passed_time":2.480918877,"remaining_time":4.527326538},
{"learn":[0.2672259579],"iteration":354,"passed_time":2.489054754,"remaining_time":4.522367089},
{"learn":[0.2669943054],"iteration":355,"passed_time":2.49602706,"remaining_time":4.515284906},
{"learn":[0.2668325781],"iteration":356,"passed_time":2.502215522,"remaining_time":4.506791542},
{"learn":[0.2668041125],"iteration":357,"passed_time":2.50863317,"remaining_time":4.498722053},
{"learn":[0.2665614565],"iteration":358,"passed_time":2.514857756,"remaining_time":4.490317051},
{"learn":[0.2663890975],"iteration":359,"passed_time":2.5215722,"remaining_time":4.482795023},
{"learn":[0.266260382],"iteration":360,"passed_time":2.52834555,"remaining_time":4.475381736},
{"learn":[0.2661780982],"iteration":361,"passed_time":2.537150061,"remaining_time":4.471551765},
{"learn":[0.2661588998],"iteration":362,"passed_time":2.542796887,"remaining_time":4.462153215},
{"learn":[0.2660414548],"iteration":363,"passed_time":2.549840709,"remaining_time":4.455216183},
{"learn":[0.2657694054],"iteration":364,"passed_time":2.556848978,"remaining_time":4.448216715},
{"learn":[0.2656711323],"iteration":365,"passed_time":2.56343283,"remaining_time":4.440482006},
{"learn":[0.2654990692],"iteration":366,"passed_time":2.570224654,"remaining_time":4.433112278},
{"learn":[0.265384699],"iteration":367,"passed_time":2.577460272,"remaining_time":4.426507859},
{"learn":[0.2652139419],"iteration":368,"passed_time":2.583826214,"remaining_time":4.418412848},
{"learn":[0.2651985902],"iteration":369,"passed_time":2.591188599,"remaining_time":4.41202383},
{"learn":[0.2651116676],"iteration":370,"passed_time":2.598018153,"remaining_time":4.404726195},
{"learn":[0.2650998712],"iteration":371,"passed_time":2.604553914,"remaining_time":4.396935101},
{"learn":[0.2649513302],"iteration":372,"passed_time":2.610954363,"remaining_time":4.388923285},
{"learn":[0.2648435895],"iteration":373,"passed_time":2.617085465,"remaining_time":4.380469254},
{"learn":[0.2647301542],"iteration":374,"passed_time":2.62425014,"remaining_time":4.373750233},
{"learn":[0.2646569496],"iteration":375,"passed_time":2.631095056,"remaining_time":4.366498178},
{"learn":[0.2645066849],"iteration":376,"passed_time":2.638181678,"remaining_time":4.359647707},
{"learn":[0.264240518],"iteration":377,"passed_time":2.644506365,"remaining_time":4.351542219},
{"learn":[0.2640427268],"iteration":378,"passed_time":2.651159805,"remaining_time":4.3439848},
{"learn":[0.2639659726],"iteration":379,"passed_time":2.658526608,"remaining_time":4.337596045},
{"learn":[0.2637796458],"iteration":380,"passed_time":2.664971113,"remaining_time":4.329703725},
{"learn":[0.2636136585],"iteration":381,"passed_time":2.671928328,"remaining_time":4.322648448},
{"learn":[0.2634988714],"iteration":382,"passed_time":2.678551408,"remaining_time":4.315055401},
{"learn":[0.2633747937],"iteration":383,"passed_time":2.685314848,"remaining_time":4.307692569},
{"learn":[0.2633638347],"iteration":384,"passed_time":2.691839644,"remaining_time":4.29995164},
{"learn":[0.2631327111],"iteration":385,"passed_time":2.6978789,"remaining_time":4.291444674},
{"learn":[0.2630087414],"iteration":386,"passed_time":2.705314206,"remaining_time":4.285161779},
{"learn":[0.2628889709],"iteration":387,"passed_time":2.711866091,"remaining_time":4.277479504},
{"learn":[0.262701085],"iteration":388,"passed_time":2.720117651,"remaining_time":4.272472711},
{"learn":[0.2625894857],"iteration":389,"passed_time":2.726346132,"remaining_time":4.264284976},
{"learn":[0.2624745415],"iteration":390,"passed_time":2.732329775,"remaining_time":4.255725916},
{"learn":[0.2622601324],"iteration":391,"passed_time":2.740565171,"remaining_time":4.250672509},
{"learn":[0.2622502335],"iteration":392,"passed_time":2.746636865,"remaining_time":4.242261011},
{"learn":[0.2621175754],"iteration":393,"passed_time":2.754365635,"remaining_time":4.236410089},
{"learn":[0.2618267544],"iteration":394,"passed_time":2.762140951,"remaining_time":4.230620951},
{"learn":[0.2616117547],"iteration":395,"passed_time":2.768891671,"remaining_time":4.223259013},
{"learn":[0.2614515762],"iteration":396,"passed_time":2.775385483,"remaining_time":4.21550994},
{"learn":[0.2613039456],"iteration":397,"passed_time":2.782651081,"remaining_time":4.20893455},
{"learn":[0.2611851492],"iteration":398,"passed_time":2.79114733,"remaining_time":4.204209386},
{"learn":[0.2610627815],"iteration":399,"passed_time":2.797790017,"remaining_time":4.196685026},
{"learn":[0.2609686891],"iteration":400,"passed_time":2.806145071,"remaining_time":4.191722936},
{"learn":[0.2606837512],"iteration":401,"passed_time":2.813240107,"remaining_time":4.184869612},
{"learn":[0.2605367103],"iteration":402,"passed_time":2.820548014,"remaining_time":4.178330433},
{"learn":[0.2605044629],"iteration":403,"passed_time":2.82663482,"remaining_time":4.169986021},
{"learn":[0.2604917677],"iteration":404,"passed_time":2.832631113,"remaining_time":4.161519783},
{"learn":[0.2604110415],"iteration":405,"passed_time":2.840116761,"remaining_time":4.155244719},
{"learn":[0.2602793164],"iteration":406,"passed_time":2.846891978,"remaining_time":4.147928607},
{"learn":[0.2600400516],"iteration":407,"passed_time":2.854679111,"remaining_time":4.142083417},
{"learn":[0.260029028],"iteration":408,"passed_time":2.861179209,"remaining_time":4.134368979},
{"learn":[0.259866183],"iteration":409,"passed_time":2.868163312,"remaining_time":4.127356961},
{"learn":[0.2596419683],"iteration":410,"passed_time":2.875366641,"remaining_time":4.120659249},
{"learn":[0.2595399535],"iteration":411,"passed_time":2.882534237,"remaining_time":4.113908086},
{"learn":[0.2593192647],"iteration":412,"passed_time":2.889119887,"remaining_time":4.106327781},
{"learn":[0.2590755193],"iteration":413,"passed_time":2.895732956,"remaining_time":4.098791092},
{"learn":[0.2589827507],"iteration":414,"passed_time":2.90250229,"remaining_time":4.091479132},
{"learn":[0.2587447754],"iteration":415,"passed_time":2.909577989,"remaining_time":4.084599869},
{"learn":[0.258532716],"iteration":416,"passed_time":2.917643133,"remaining_time":4.07910299},
{"learn":[0.2583728597],"iteration":417,"passed_time":2.924186916,"remaining_time":4.071475562},
{"learn":[0.2582859366],"iteration":418,"passed_time":2.930609754,"remaining_time":4.063685602},
{"learn":[0.2582020117],"iteration":419,"passed_time":2.938515181,"remaining_time":4.057949535},
{"learn":[0.2579790128],"iteration":420,"passed_time":2.945539022,"remaining_time":4.050990722},
{"learn":[0.2577607518],"iteration":421,"passed_time":2.953650151,"remaining_time":4.045520822},
{"learn":[0.2575765461],"iteration":422,"passed_time":2.959986785,"remaining_time":4.037617907},
{"learn":[0.2575092096],"iteration":423,"passed_time":2.968135503,"remaining_time":4.03218408},
{"learn":[0.2574094881],"iteration":424,"passed_time":2.974767388,"remaining_time":4.02468529},
{"learn":[0.2572804559],"iteration":425,"passed_time":2.981501381,"remaining_time":4.017328151},
{"learn":[0.2572690343],"iteration":426,"passed_time":2.988114068,"remaining_time":4.00981115},
{"learn":[0.257049075],"iteration":427,"passed_time":2.994774447,"remaining_time":4.002362111},
{"learn":[0.2569633133],"iteration":428,"passed_time":3.001668148,"remaining_time":3.995227302},
{"learn":[0.2568280357],"iteration":429,"passed_time":3.008082402,"remaining_time":3.987458068},
{"learn":[0.2566202887],"iteration":430,"passed_time":3.015378613,"remaining_time":3.980859468},
{"learn":[0.2565633534],"iteration":431,"passed_time":3.022751791,"remaining_time":3.974358836},
{"learn":[0.256551828],"iteration":432,"passed_time":3.028464119,"remaining_time":3.965679343},
{"learn":[0.256428152],"iteration":433,"passed_time":3.035948482,"remaining_time":3.959324518},
{"learn":[0.2561819969],"iteration":434,"passed_time":3.042786942,"remaining_time":3.952125569},
{"learn":[0.2560730615],"iteration":435,"passed_time":3.051166072,"remaining_time":3.946921249},
{"learn":[0.2560597534],"iteration":436,"passed_time":3.0571585,"remaining_time":3.938627541},
{"learn":[0.2560393097],"iteration":437,"passed_time":3.06272362,"remaining_time":3.92979606},
{"learn":[0.2559260034],"iteration":438,"passed_time":3.06974712,"remaining_time":3.92284313},
{"learn":[0.2557135266],"iteration":439,"passed_time":3.076526926,"remaining_time":3.915579723},
{"learn":[0.2555707974],"iteration":440,"passed_time":3.083863357,"remaining_time":3.909024074},
{"learn":[0.2554328778],"iteration":441,"passed_time":3.090531145,"remaining_time":3.901620767},
{"learn":[0.2554111293],"iteration":442,"passed_time":3.096994576,"remaining_time":3.893963835},
{"learn":[0.2551779008],"iteration":443,"passed_time":3.10508953,"remaining_time":3.888355357},
{"learn":[0.2550176856],"iteration":444,"passed_time":3.111599186,"remaining_time":3.880758535},
{"learn":[0.254921476],"iteration":445,"passed_time":3.119395485,"remaining_time":3.874764796},
{"learn":[0.254760576],"iteration":446,"passed_time":3.126274096,"remaining_time":3.867627685},
{"learn":[0.2546656778],"iteration":447,"passed_time":3.133720869,"remaining_time":3.861191785},
{"learn":[0.2545301626],"iteration":448,"passed_time":3.140902622,"remaining_time":3.854426157},
{"learn":[0.2543022343],"iteration":449,"passed_time":3.14785823,"remaining_time":3.847382281},
{"learn":[0.2540572885],"iteration":450,"passed_time":3.154755817,"remaining_time":3.840268167},
{"learn":[0.2537639524],"iteration":451,"passed_time":3.161443304,"remaining_time":3.832900289},
{"learn":[0.2536488263],"iteration":452,"passed_time":3.169040909,"remaining_time":3.826634387},
{"learn":[0.2536351927],"iteration":453,"passed_time":3.175530224,"remaining_time":3.81902974},
{"learn":[0.253496002],"iteration":454,"passed_time":3.183314706,"remaining_time":3.812981351},
{"learn":[0.2532447886],"iteration":455,"passed_time":3.189555156,"remaining_time":3.805083344},
{"learn":[0.2532228805],"iteration":456,"passed_time":3.195636961,"remaining_time":3.797004092},
{"learn":[0.2530332892],"iteration":457,"passed_time":3.203674897,"remaining_time":3.791248459},
{"learn":[0.2528211999],"iteration":458,"passed_time":3.210270747,"remaining_time":3.783783168},
{"learn":[0.2527412106],"iteration":459,"passed_time":3.217999838,"remaining_time":3.777651984},
{"learn":[0.2526661388],"iteration":460,"passed_time":3.224245469,"remaining_time":3.769779409},
{"learn":[0.2525167814],"iteration":461,"passed_time":3.231333577,"remaining_time":3.762894945},
{"learn":[0.2523990398],"iteration":462,"passed_time":3.238644808,"remaining_time":3.756268384},
{"learn":[0.2522143732],"iteration":463,"passed_time":3.245209202,"remaining_time":3.748776147},
{"learn":[0.2521595811],"iteration":464,"passed_time":3.252707882,"remaining_time":3.742362832},
{"learn":[0.2520535937],"iteration":465,"passed_time":3.260100076,"remaining_time":3.735822834},
{"learn":[0.2518828018],"iteration":466,"passed_time":3.267273827,"remaining_time":3.729029871},
{"learn":[0.2517323625],"iteration":467,"passed_time":3.273772399,"remaining_time":3.72146777},
{"learn":[0.2515518509],"iteration":468,"passed_time":3.280412978,"remaining_time":3.714070984},
{"learn":[0.2513747907],"iteration":469,"passed_time":3.287376699,"remaining_time":3.70704181},
{"learn":[0.2512598032],"iteration":470,"passed_time":3.293998182,"remaining_time":3.699628531},
{"learn":[0.2512477851],"iteration":471,"passed_time":3.301560476,"remaining_time":3.693271041},
{"learn":[0.2511008519],"iteration":472,"passed_time":3.308791496,"remaining_time":3.686539363},
{"learn":[0.25099875],"iteration":473,"passed_time":3.316617003,"remaining_time":3.680465282},
{"learn":[0.2509572403],"iteration":474,"passed_time":3.32256422,"remaining_time":3.672307822},
{"learn":[0.250860697],"iteration":475,"passed_time":3.329280683,"remaining_time":3.665006466},
{"learn":[0.2506415226],"iteration":476,"passed_time":3.3365711,"remaining_time":3.658336866},
{"learn":[0.25057203],"iteration":477,"passed_time":3.342916921,"remaining_time":3.650633123},
{"learn":[0.2503407189],"iteration":478,"passed_time":3.349847851,"remaining_time":3.643571462},
{"learn":[0.2501766125],"iteration":479,"passed_time":3.356347496,"remaining_time":3.636043121},
{"learn":[0.250099765],"iteration":480,"passed_time":3.362658257,"remaining_time":3.62831525},
{"learn":[0.2499389871],"iteration":481,"passed_time":3.369960421,"remaining_time":3.62165871},
{"learn":[0.2498051462],"iteration":482,"passed_time":3.376726221,"remaining_time":3.614425376},
{"learn":[0.2497105355],"iteration":483,"passed_time":3.384105634,"remaining_time":3.607848156},
{"learn":[0.2496555576],"iteration":484,"passed_time":3.391454044,"remaining_time":3.601234706},
{"learn":[0.2495011806],"iteration":485,"passed_time":3.399438716,"remaining_time":3.595291153},
{"learn":[0.2492233821],"iteration":486,"passed_time":3.405969708,"remaining_time":3.587807926},
{"learn":[0.2490728867],"iteration":487,"passed_time":3.413479311,"remaining_time":3.581355343},
{"learn":[0.249054526],"iteration":488,"passed_time":3.420032722,"remaining_time":3.573899225},
{"learn":[0.2488360564],"iteration":489,"passed_time":3.427133852,"remaining_time":3.567016867},
{"learn":[0.2486891704],"iteration":490,"passed_time":3.435047642,"remaining_time":3.560976069},
{"learn":[0.2486454487],"iteration":491,"passed_time":3.441490611,"remaining_time":3.553409005},
{"learn":[0.2485156261],"iteration":492,"passed_time":3.449658707,"remaining_time":3.547620618},
{"learn":[0.2482023335],"iteration":493,"passed_time":3.456940972,"remaining_time":3.540915247},
{"learn":[0.2481305382],"iteration":494,"passed_time":3.464252424,"remaining_time":3.534237321},
{"learn":[0.2479861882],"iteration":495,"passed_time":3.471217038,"remaining_time":3.52720441},
{"learn":[0.2478680597],"iteration":496,"passed_time":3.478622475,"remaining_time":3.520617918},
{"learn":[0.2477077316],"iteration":497,"passed_time":3.485754289,"remaining_time":3.513752315},
{"learn":[0.2474834566],"iteration":498,"passed_time":3.492623281,"remaining_time":3.506621771},
{"learn":[0.2473976243],"iteration":499,"passed_time":3.501862379,"remaining_time":3.501862379},
{"learn":[0.2473360248],"iteration":500,"passed_time":3.508474173,"remaining_time":3.494468289},
{"learn":[0.2472491175],"iteration":501,"passed_time":3.515914088,"remaining_time":3.487898837},
{"learn":[0.247125224],"iteration":502,"passed_time":3.52454628,"remaining_time":3.482503979},
{"learn":[0.2471080342],"iteration":503,"passed_time":3.532146697,"remaining_time":3.476080876},
{"learn":[0.2469514285],"iteration":504,"passed_time":3.538431684,"remaining_time":3.46836373},
{"learn":[0.2469343685],"iteration":505,"passed_time":3.545225747,"remaining_time":3.461149247},
{"learn":[0.2468046972],"iteration":506,"passed_time":3.55253492,"remaining_time":3.454437308},
{"learn":[0.2465748066],"iteration":507,"passed_time":3.559431773,"remaining_time":3.447323686},
{"learn":[0.2463839851],"iteration":508,"passed_time":3.568365049,"remaining_time":3.442175322},
{"learn":[0.2461432209],"iteration":509,"passed_time":3.575368569,"remaining_time":3.435158037},
{"learn":[0.2459938963],"iteration":510,"passed_time":3.582703655,"remaining_time":3.428458097},
{"learn":[0.2458427837],"iteration":511,"passed_time":3.589013623,"remaining_time":3.420778609},
{"learn":[0.2456569383],"iteration":512,"passed_time":3.59651412,"remaining_time":3.414234652},
{"learn":[0.2454680982],"iteration":513,"passed_time":3.603510501,"remaining_time":3.407210319},
{"learn":[0.2453727065],"iteration":514,"passed_time":3.612264751,"remaining_time":3.401841562},
{"learn":[0.2452420271],"iteration":515,"passed_time":3.618934346,"remaining_time":3.394504309},
{"learn":[0.2450313552],"iteration":516,"passed_time":3.62610122,"remaining_time":3.387634215},
{"learn":[0.2448994809],"iteration":517,"passed_time":3.633286627,"remaining_time":3.380780221},
{"learn":[0.2447966224],"iteration":518,"passed_time":3.640325017,"remaining_time":3.373788696},
{"learn":[0.2447368942],"iteration":519,"passed_time":3.648546758,"remaining_time":3.367889315},
{"learn":[0.2446685744],"iteration":520,"passed_time":3.654977327,"remaining_time":3.360334241},
{"learn":[0.2445655052],"iteration":521,"passed_time":3.663773033,"remaining_time":3.354949252},
{"learn":[0.244549183],"iteration":522,"passed_time":3.670497377,"remaining_time":3.347662044},
{"learn":[0.2444771615],"iteration":523,"passed_time":3.678758425,"remaining_time":3.34177292},
{"learn":[0.2441904245],"iteration":524,"passed_time":3.685440942,"remaining_time":3.334446566},
{"learn":[0.2440241024],"iteration":525,"passed_time":3.695031716,"remaining_time":3.329743409},
{"learn":[0.243885714],"iteration":526,"passed_time":3.703963234,"remaining_time":3.32443},
{"learn":[0.243876671],"iteration":527,"passed_time":3.712091803,"remaining_time":3.318385096},
{"learn":[0.2437689193],"iteration":528,"passed_time":3.719885713,"remaining_time":3.312034349},
{"learn":[0.2437010393],"iteration":529,"passed_time":3.727765788,"remaining_time":3.305754567},
{"learn":[0.2436609309],"iteration":530,"passed_time":3.734423385,"remaining_time":3.298389016},
{"learn":[0.2435592318],"iteration":531,"passed_time":3.741904866,"remaining_time":3.291750897},
{"learn":[0.243297572],"iteration":532,"passed_time":3.749225605,"remaining_time":3.284968776},
{"learn":[0.2432627252],"iteration":533,"passed_time":3.756057569,"remaining_time":3.277758103},
{"learn":[0.2432317917],"iteration":534,"passed_time":3.764112985,"remaining_time":3.271612221},
{"learn":[0.2430058158],"iteration":535,"passed_time":3.771058533,"remaining_time":3.264498432},
{"learn":[0.2429890967],"iteration":536,"passed_time":3.779505043,"remaining_time":3.258679395},
{"learn":[0.2428302226],"iteration":537,"passed_time":3.786358905,"remaining_time":3.251482926},
{"learn":[0.242711232],"iteration":538,"passed_time":3.793089072,"remaining_time":3.244181934},
{"learn":[0.2425251306],"iteration":539,"passed_time":3.800500975,"remaining_time":3.237463794},
{"learn":[0.2424267253],"iteration":540,"passed_time":3.807475239,"remaining_time":3.230371783},
{"learn":[0.2423213674],"iteration":541,"passed_time":3.816079629,"remaining_time":3.224657694},
{"learn":[0.2421625121],"iteration":542,"passed_time":3.822796473,"remaining_time":3.217344361},
{"learn":[0.2421070584],"iteration":543,"passed_time":3.830660042,"remaining_time":3.210994447},
{"learn":[0.2420703545],"iteration":544,"passed_time":3.836843423,"remaining_time":3.203236253},
{"learn":[0.2418485758],"iteration":545,"passed_time":3.844114172,"remaining_time":3.196387975},
{"learn":[0.2416358829],"iteration":546,"passed_time":3.85100208,"remaining_time":3.189221101},
{"learn":[0.2415908481],"iteration":547,"passed_time":3.857707187,"remaining_time":3.181904468},
{"learn":[0.2413990646],"iteration":548,"passed_time":3.866068526,"remaining_time":3.175950647},
{"learn":[0.24137778],"iteration":549,"passed_time":3.872220683,"remaining_time":3.168180559},
{"learn":[0.2412142633],"iteration":550,"passed_time":3.880417263,"remaining_time":3.162082307},
{"learn":[0.2410986721],"iteration":551,"passed_time":3.887276567,"remaining_time":3.154891127},
{"learn":[0.2409050039],"iteration":552,"passed_time":3.895304814,"remaining_time":3.148646025},
{"learn":[0.240715753],"iteration":553,"passed_time":3.901322031,"remaining_time":3.140775498},
{"learn":[0.2406321308],"iteration":554,"passed_time":3.908064056,"remaining_time":3.133492801},
{"learn":[0.2405233675],"iteration":555,"passed_time":3.916469149,"remaining_time":3.127540112},
{"learn":[0.2404614367],"iteration":556,"passed_time":3.923313182,"remaining_time":3.120337055},
{"learn":[0.2403053427],"iteration":557,"passed_time":3.930365447,"remaining_time":3.113300229},
{"learn":[0.2402031149],"iteration":558,"passed_time":3.936370526,"remaining_time":3.105437213},
{"learn":[0.240019739],"iteration":559,"passed_time":3.944380359,"remaining_time":3.099155997},
{"learn":[0.2398857143],"iteration":560,"passed_time":3.951304583,"remaining_time":3.092019094},
{"learn":[0.2397972367],"iteration":561,"passed_time":3.957542572,"remaining_time":3.084348126},
{"learn":[0.2397848861],"iteration":562,"passed_time":3.964533291,"remaining_time":3.077266516},
{"learn":[0.2396922628],"iteration":563,"passed_time":3.971703869,"remaining_time":3.070324268},
{"learn":[0.2396840411],"iteration":564,"passed_time":3.97993305,"remaining_time":3.064196242},
{"learn":[0.2395527432],"iteration":565,"passed_time":3.986765376,"remaining_time":3.056989705},
{"learn":[0.2394163961],"iteration":566,"passed_time":3.995006273,"remaining_time":3.05086017},
{"learn":[0.2392988843],"iteration":567,"passed_time":4.00236402,"remaining_time":3.044051508},
{"learn":[0.2391916796],"iteration":568,"passed_time":4.009681094,"remaining_time":3.037210108},
{"learn":[0.2390395745],"iteration":569,"passed_time":4.016939332,"remaining_time":3.030322654},
{"learn":[0.2389118736],"iteration":570,"passed_time":4.024052631,"remaining_time":3.023325007},
{"learn":[0.2387369622],"iteration":571,"passed_time":4.031848038,"remaining_time":3.016837343},
{"learn":[0.238615906],"iteration":572,"passed_time":4.038517713,"remaining_time":3.009506219},
{"learn":[0.2383471589],"iteration":573,"passed_time":4.047110638,"remaining_time":3.003604759},
{"learn":[0.2382379693],"iteration":574,"passed_time":4.054253054,"remaining_time":2.996621822},
{"learn":[0.2380567899],"iteration":575,"passed_time":4.062782414,"remaining_time":2.990659277},
{"learn":[0.2380353541],"iteration":576,"passed_time":4.069575845,"remaining_time":2.98341522},
{"learn":[0.2378078919],"iteration":577,"passed_time":4.076917195,"remaining_time":2.976572762},
{"learn":[0.2378000779],"iteration":578,"passed_time":4.083905224,"remaining_time":2.969471674},
{"learn":[0.2377358226],"iteration":579,"passed_time":4.091244406,"remaining_time":2.96262526},
{"learn":[0.2376688897],"iteration":580,"passed_time":4.098153659,"remaining_time":2.955467097},
{"learn":[0.237580807],"iteration":581,"passed_time":4.10524741,"remaining_time":2.948442298},
{"learn":[0.2373643804],"iteration":582,"passed_time":4.113252977,"remaining_time":2.942069454},
{"learn":[0.2372606336],"iteration":583,"passed_time":4.12054476,"remaining_time":2.935182569},
{"learn":[0.2371328514],"iteration":584,"passed_time":4.128685818,"remaining_time":2.928896777},
{"learn":[0.2370929604],"iteration":585,"passed_time":4.135837862,"remaining_time":2.92190593},
{"learn":[0.2369076757],"iteration":586,"passed_time":4.14398648,"remaining_time":2.915615701},
{"learn":[0.2368511433],"iteration":587,"passed_time":4.151204107,"remaining_time":2.908666823},
{"learn":[0.2367633868],"iteration":588,"passed_time":4.158331462,"remaining_time":2.901654042},
{"learn":[0.2366107005],"iteration":589,"passed_time":4.16607472,"remaining_time":2.895068873},
{"learn":[0.2366029808],"iteration":590,"passed_time":4.17256543,"remaining_time":2.887612962},
{"learn":[0.2365089179],"iteration":591,"passed_time":4.1800941,"remaining_time":2.880875663},
{"learn":[0.2364011352],"iteration":592,"passed_time":4.186761858,"remaining_time":2.873544816},
{"learn":[0.2361695702],"iteration":593,"passed_time":4.195726087,"remaining_time":2.867785844},
{"learn":[0.2361340499],"iteration":594,"passed_time":4.202261405,"remaining_time":2.860362805},
{"learn":[0.2358931586],"iteration":595,"passed_time":4.209689453,"remaining_time":2.853547884},
{"learn":[0.2358689419],"iteration":596,"passed_time":4.216260494,"remaining_time":2.846152394},
{"learn":[0.2358431874],"iteration":597,"passed_time":4.223480681,"remaining_time":2.839196043},
{"learn":[0.2358190854],"iteration":598,"passed_time":4.23099921,"remaining_time":2.832438536},
{"learn":[0.2357388762],"iteration":599,"passed_time":4.237784638,"remaining_time":2.825189759},
{"learn":[0.2356762438],"iteration":600,"passed_time":4.246550444,"remaining_time":2.819257283},
{"learn":[0.2354912189],"iteration":601,"passed_time":4.253084598,"remaining_time":2.811839983},
{"learn":[0.2354310071],"iteration":602,"passed_time":4.261443708,"remaining_time":2.805627118},
{"learn":[0.2353231996],"iteration":603,"passed_time":4.268668081,"remaining_time":2.798663179},
{"learn":[0.2351829703],"iteration":604,"passed_time":4.276096319,"remaining_time":2.791831481},
{"learn":[0.2350401851],"iteration":605,"passed_time":4.283510873,"remaining_time":2.784988917},
{"learn":[0.2349560633],"iteration":606,"passed_time":4.290269956,"remaining_time":2.777720087},
{"learn":[0.2348783569],"iteration":607,"passed_time":4.297283667,"remaining_time":2.770617101},
{"learn":[0.2347243973],"iteration":608,"passed_time":4.303939447,"remaining_time":2.763284604},
{"learn":[0.2346120401],"iteration":609,"passed_time":4.311954783,"remaining_time":2.75682355},
{"learn":[0.2345995447],"iteration":610,"passed_time":4.318673113,"remaining_time":2.749531654},
{"learn":[0.2343813569],"iteration":611,"passed_time":4.327124602,"remaining_time":2.743340434},
{"learn":[0.2343722198],"iteration":612,"passed_time":4.333282291,"remaining_time":2.735693714},
{"learn":[0.2342680933],"iteration":613,"passed_time":4.340242889,"remaining_time":2.728556605},
{"learn":[0.2340855557],"iteration":614,"passed_time":4.347074071,"remaining_time":2.721339052},
{"learn":[0.2340072566],"iteration":615,"passed_time":4.353893886,"remaining_time":2.714115669},
{"learn":[0.2337893443],"iteration":616,"passed_time":4.361563389,"remaining_time":2.707421034},
{"learn":[0.233701257],"iteration":617,"passed_time":4.368550524,"remaining_time":2.700301457},
{"learn":[0.2336936513],"iteration":618,"passed_time":4.375306143,"remaining_time":2.693039807},
{"learn":[0.2334312124],"iteration":619,"passed_time":4.382329182,"remaining_time":2.685943692},
{"learn":[0.2332986881],"iteration":620,"passed_time":4.38975504,"remaining_time":2.679093656},
{"learn":[0.2332194787],"iteration":621,"passed_time":4.397155508,"remaining_time":2.672226337},
{"learn":[0.2331214312],"iteration":622,"passed_time":4.404302803,"remaining_time":2.665204104},
{"learn":[0.2330360217],"iteration":623,"passed_time":4.414206488,"remaining_time":2.659842371},
{"learn":[0.2330296009],"iteration":624,"passed_time":4.423633226,"remaining_time":2.654179936},
{"learn":[0.232895579],"iteration":625,"passed_time":4.431159969,"remaining_time":2.647370333},
{"learn":[0.2326968494],"iteration":626,"passed_time":4.437271914,"remaining_time":2.639716785},
{"learn":[0.2326314925],"iteration":627,"passed_time":4.444348426,"remaining_time":2.632639514},
{"learn":[0.2325158977],"iteration":628,"passed_time":4.451490832,"remaining_time":2.625601111},
{"learn":[0.2324970825],"iteration":629,"passed_time":4.458810546,"remaining_time":2.618666511},
{"learn":[0.2324906335],"iteration":630,"passed_time":4.464835655,"remaining_time":2.610973624},
{"learn":[0.2322980292],"iteration":631,"passed_time":4.471899135,"remaining_time":2.603890636},
{"learn":[0.2322236383],"iteration":632,"passed_time":4.478741611,"remaining_time":2.596679576},
{"learn":[0.2320774181],"iteration":633,"passed_time":4.485393034,"remaining_time":2.589359386},
{"learn":[0.2320574893],"iteration":634,"passed_time":4.493309193,"remaining_time":2.582768276},
{"learn":[0.231848824],"iteration":635,"passed_time":4.500383115,"remaining_time":2.575690965},
{"learn":[0.2318382815],"iteration":636,"passed_time":4.50806079,"remaining_time":2.568957719},
{"learn":[0.2318295422],"iteration":637,"passed_time":4.514353579,"remaining_time":2.56143573},
{"learn":[0.231702348],"iteration":638,"passed_time":4.521073415,"remaining_time":2.554158846},
{"learn":[0.2316962393],"iteration":639,"passed_time":4.527635601,"remaining_time":2.546795026},
{"learn":[0.2315218983],"iteration":640,"passed_time":4.534223088,"remaining_time":2.539447876},
{"learn":[0.2313289116],"iteration":641,"passed_time":4.541025876,"remaining_time":2.532223152},
{"learn":[0.2311857525],"iteration":642,"passed_time":4.54765011,"remaining_time":2.524900605},
{"learn":[0.2311032589],"iteration":643,"passed_time":4.554612194,"remaining_time":2.517766989},
{"learn":[0.2310328701],"iteration":644,"passed_time":4.561471568,"remaining_time":2.510577375},
{"learn":[0.2308992611],"iteration":645,"passed_time":4.568134266,"remaining_time":2.503281006},
{"learn":[0.2308145356],"iteration":646,"passed_time":4.576146891,"remaining_time":2.49672311},
{"learn":[0.2307777301],"iteration":647,"passed_time":4.582557852,"remaining_time":2.489290685},
{"learn":[0.2305955486],"iteration":648,"passed_time":4.590159604,"remaining_time":2.482505425},
{"learn":[0.2304804159],"iteration":649,"passed_time":4.597721095,"remaining_time":2.475695974},
{"learn":[0.2303790646],"iteration":650,"passed_time":4.605031924,"remaining_time":2.468749833},
{"learn":[0.2302372506],"iteration":651,"passed_time":4.61217707,"remaining_time":2.461714142},
{"learn":[0.2300502096],"iteration":652,"passed_time":4.619311484,"remaining_time":2.454672412},
{"learn":[0.229960595],"iteration":653,"passed_time":4.628540883,"remaining_time":2.448738755},
{"learn":[0.229832088],"iteration":654,"passed_time":4.635556723,"remaining_time":2.441629114},
{"learn":[0.2297891072],"iteration":655,"passed_time":4.64316975,"remaining_time":2.434832918},
{"learn":[0.2296408808],"iteration":656,"passed_time":4.649818944,"remaining_time":2.427531047},
{"learn":[0.2294332742],"iteration":657,"passed_time":4.657603296,"remaining_time":2.420821166},
{"learn":[0.2294227248],"iteration":658,"passed_time":4.664621374,"remaining_time":2.413711515},
{"learn":[0.229352589],"iteration":659,"passed_time":4.67223901,"remaining_time":2.406911005},
{"learn":[0.2292755639],"iteration":660,"passed_time":4.678818705,"remaining_time":2.399575705},
{"learn":[0.2291233489],"iteration":661,"passed_time":4.685189536,"remaining_time":2.392136047},
{"learn":[0.2291166889],"iteration":662,"passed_time":4.692363237,"remaining_time":2.385107709},
{"learn":[0.2289818275],"iteration":663,"passed_time":4.698598897,"remaining_time":2.377604261},
{"learn":[0.2289503442],"iteration":664,"passed_time":4.70574819,"remaining_time":2.370564878},
{"learn":[0.2288923797],"iteration":665,"passed_time":4.713143487,"remaining_time":2.363648536},
{"learn":[0.2288306579],"iteration":666,"passed_time":4.720365661,"remaining_time":2.356644326},
{"learn":[0.228719995],"iteration":667,"passed_time":4.728073046,"remaining_time":2.349880616},
{"learn":[0.2285659797],"iteration":668,"passed_time":4.735121606,"remaining_time":2.342788119},
{"learn":[0.2285437909],"iteration":669,"passed_time":4.742610989,"remaining_time":2.335912875},
{"learn":[0.2284655666],"iteration":670,"passed_time":4.74969221,"remaining_time":2.328835674},
{"learn":[0.2282580713],"iteration":671,"passed_time":4.757864694,"remaining_time":2.3222911},
{"learn":[0.2281508346],"iteration":672,"passed_time":4.764845132,"remaining_time":2.315162493},
{"learn":[0.2280929361],"iteration":673,"passed_time":4.771794556,"remaining_time":2.308019325},
{"learn":[0.2279746531],"iteration":674,"passed_time":4.778943899,"remaining_time":2.300972988},
{"learn":[0.2279491969],"iteration":675,"passed_time":4.785711657,"remaining_time":2.293743457},
{"learn":[0.2278513624],"iteration":676,"passed_time":4.792754524,"remaining_time":2.286646546},
{"learn":[0.227766361],"iteration":677,"passed_time":4.799372353,"remaining_time":2.279347931},
{"learn":[0.2276206334],"iteration":678,"passed_time":4.806331807,"remaining_time":2.272212828},
{"learn":[0.2276138449],"iteration":679,"passed_time":4.812775007,"remaining_time":2.264835297},
{"learn":[0.2275340357],"iteration":680,"passed_time":4.820505975,"remaining_time":2.258063739},
{"learn":[0.2273971046],"iteration":681,"passed_time":4.827180751,"remaining_time":2.25079689},
{"learn":[0.2272415124],"iteration":682,"passed_time":4.834340346,"remaining_time":2.243756793},
{"learn":[0.2271677567],"iteration":683,"passed_time":4.842022489,"remaining_time":2.236957758},
{"learn":[0.227163601],"iteration":684,"passed_time":4.849059513,"remaining_time":2.229859484},
{"learn":[0.2270610167],"iteration":685,"passed_time":4.857507177,"remaining_time":2.223407075},
{"learn":[0.2269847113],"iteration":686,"passed_time":4.864439483,"remaining_time":2.216258454},
{"learn":[0.2268618278],"iteration":687,"passed_time":4.872114799,"remaining_time":2.209447409},
{"learn":[0.2267843078],"iteration":688,"passed_time":4.878930428,"remaining_time":2.20224581},
{"learn":[0.2266896454],"iteration":689,"passed_time":4.8860594,"remaining_time":2.195186107},
{"learn":[0.2266443662],"iteration":690,"passed_time":4.89363071,"remaining_time":2.188324008},
{"learn":[0.2265085148],"iteration":691,"passed_time":4.900683899,"remaining_time":2.18122925},
{"learn":[0.2263458441],"iteration":692,"passed_time":4.908564084,"remaining_time":2.174500972},
{"learn":[0.2262487961],"iteration":693,"passed_time":4.915319091,"remaining_time":2.167273259},
{"learn":[0.226125278],"iteration":694,"passed_time":4.922761747,"remaining_time":2.16034868},
{"learn":[0.2259279321],"iteration":695,"passed_time":4.92983358,"remaining_time":2.153260644},
{"learn":[0.2258155577],"iteration":696,"passed_time":4.937800874,"remaining_time":2.146561929},
{"learn":[0.225737904],"iteration":697,"passed_time":4.944766302,"remaining_time":2.139426108},
{"learn":[0.2257321369],"iteration":698,"passed_time":4.95124142,"remaining_time":2.132079638},
{"learn":[0.2257233832],"iteration":699,"passed_time":4.958211416,"remaining_time":2.12494775},
{"learn":[0.2255023977],"iteration":700,"passed_time":4.964581182,"remaining_time":2.117560305},
{"learn":[0.2254060627],"iteration":701,"passed_time":4.972275886,"remaining_time":2.110738197},
{"learn":[0.2253799824],"iteration":702,"passed_time":4.979151254,"remaining_time":2.103567457},
{"learn":[0.2253137978],"iteration":703,"passed_time":4.988041548,"remaining_time":2.097244742},
{"learn":[0.2252769276],"iteration":704,"passed_time":4.994795711,"remaining_time":2.0900209},
{"learn":[0.2251600812],"iteration":705,"passed_time":5.003757079,"remaining_time":2.083717537},
{"learn":[0.2250181083],"iteration":706,"passed_time":5.010447517,"remaining_time":2.07646552},
{"learn":[0.2250131812],"iteration":707,"passed_time":5.017074783,"remaining_time":2.069189035},
{"learn":[0.2249354048],"iteration":708,"passed_time":5.024497349,"remaining_time":2.062240802},
{"learn":[0.2248046307],"iteration":709,"passed_time":5.032235075,"remaining_time":2.05541996},
{"learn":[0.2246937181],"iteration":710,"passed_time":5.040516363,"remaining_time":2.048817481},
{"learn":[0.2246886825],"iteration":711,"passed_time":5.046832927,"remaining_time":2.041415566},
{"learn":[0.2245641038],"iteration":712,"passed_time":5.054975793,"remaining_time":2.034751827},
{"learn":[0.2245594107],"iteration":713,"passed_time":5.061646231,"remaining_time":2.027494149},
{"learn":[0.224549742],"iteration":714,"passed_time":5.069972952,"remaining_time":2.020898309},
{"learn":[0.2243494981],"iteration":715,"passed_time":5.076626714,"remaining_time":2.01363406},
{"learn":[0.2241539581],"iteration":716,"passed_time":5.084255996,"remaining_time":2.006756551},
{"learn":[0.2240028078],"iteration":717,"passed_time":5.090701395,"remaining_time":1.999411968},
{"learn":[0.2238557807],"iteration":718,"passed_time":5.097484725,"remaining_time":1.992201958},
{"learn":[0.22368442],"iteration":719,"passed_time":5.105123987,"remaining_time":1.985325995},
{"learn":[0.2235495336],"iteration":720,"passed_time":5.111885971,"remaining_time":1.978108441},
{"learn":[0.2233910334],"iteration":721,"passed_time":5.1200397,"remaining_time":1.971428029},
{"learn":[0.2233096412],"iteration":722,"passed_time":5.126813351,"remaining_time":1.964214797},
{"learn":[0.2231595065],"iteration":723,"passed_time":5.134339722,"remaining_time":1.957289728},
{"learn":[0.223149114],"iteration":724,"passed_time":5.141444085,"remaining_time":1.950202929},
{"learn":[0.2231317822],"iteration":725,"passed_time":5.148511883,"remaining_time":1.943102281},
{"learn":[0.2230711305],"iteration":726,"passed_time":5.155915312,"remaining_time":1.936127758},
{"learn":[0.2229136567],"iteration":727,"passed_time":5.162750047,"remaining_time":1.928939578},
{"learn":[0.2228252671],"iteration":728,"passed_time":5.170819057,"remaining_time":1.9222112},
{"learn":[0.2226626931],"iteration":729,"passed_time":5.177785168,"remaining_time":1.915071227},
{"learn":[0.2226184745],"iteration":730,"passed_time":5.186111768,"remaining_time":1.908432374},
{"learn":[0.2225345821],"iteration":731,"passed_time":5.193182045,"remaining_time":1.901328946},
{"learn":[0.2224069811],"iteration":732,"passed_time":5.200325877,"remaining_time":1.8942524},
{"learn":[0.2222803764],"iteration":733,"passed_time":5.208059285,"remaining_time":1.887389332},
{"learn":[0.222207106],"iteration":734,"passed_time":5.214824011,"remaining_time":1.880174643},
{"learn":[0.2221583143],"iteration":735,"passed_time":5.222896926,"remaining_time":1.873430419},
{"learn":[0.2220998894],"iteration":736,"passed_time":5.229539112,"remaining_time":1.86617203},
{"learn":[0.2219006489],"iteration":737,"passed_time":5.238133342,"remaining_time":1.859608314},
{"learn":[0.2217709203],"iteration":738,"passed_time":5.244403651,"remaining_time":1.852218339},
{"learn":[0.2217109076],"iteration":739,"passed_time":5.252409659,"remaining_time":1.845441232},
{"learn":[0.2215823898],"iteration":740,"passed_time":5.259053642,"remaining_time":1.838184741},
{"learn":[0.2214569387],"iteration":741,"passed_time":5.26546135,"remaining_time":1.830847747},
{"learn":[0.2214263632],"iteration":742,"passed_time":5.272605693,"remaining_time":1.823768053},
{"learn":[0.2213051551],"iteration":743,"passed_time":5.279633581,"remaining_time":1.816648114},
{"learn":[0.2212173579],"iteration":744,"passed_time":5.288223614,"remaining_time":1.810063116},
{"learn":[0.2210195931],"iteration":745,"passed_time":5.295104374,"remaining_time":1.802890765},
{"learn":[0.2208630052],"iteration":746,"passed_time":5.302703134,"remaining_time":1.795962373},
{"learn":[0.2207985436],"iteration":747,"passed_time":5.309720991,"remaining_time":1.788836484},
{"learn":[0.2206832693],"iteration":748,"passed_time":5.318567892,"remaining_time":1.782323819},
{"learn":[0.2206516249],"iteration":749,"passed_time":5.326055236,"remaining_time":1.775351745},
{"learn":[0.2206100962],"iteration":750,"passed_time":5.334690079,"remaining_time":1.768758761},
{"learn":[0.2204841818],"iteration":751,"passed_time":5.341332726,"remaining_time":1.761503346},
{"learn":[0.2203671871],"iteration":752,"passed_time":5.348307843,"remaining_time":1.754358615},
{"learn":[0.2202305636],"iteration":753,"passed_time":5.355767477,"remaining_time":1.747372413},
{"learn":[0.2201090637],"iteration":754,"passed_time":5.362363849,"remaining_time":1.740104825},
{"learn":[0.2200697329],"iteration":755,"passed_time":5.370232589,"remaining_time":1.733249671},
{"learn":[0.2198808743],"iteration":756,"passed_time":5.376934363,"remaining_time":1.726017239},
{"learn":[0.219870059],"iteration":757,"passed_time":5.385301635,"remaining_time":1.719317936},
{"learn":[0.2197134135],"iteration":758,"passed_time":5.392375888,"remaining_time":1.712203675},
{"learn":[0.2196059851],"iteration":759,"passed_time":5.400521926,"remaining_time":1.705427977},
{"learn":[0.21960075],"iteration":760,"passed_time":5.406901974,"remaining_time":1.69809405},
{"learn":[0.2194528041],"iteration":761,"passed_time":5.413860986,"remaining_time":1.690943458},
{"learn":[0.219347739],"iteration":762,"passed_time":5.4210054,"remaining_time":1.683850956},
{"learn":[0.2192400083],"iteration":763,"passed_time":5.428160185,"remaining_time":1.676761523},
{"learn":[0.219095071],"iteration":764,"passed_time":5.435823473,"remaining_time":1.669828126},
{"learn":[0.2189866737],"iteration":765,"passed_time":5.442972244,"remaining_time":1.662735646},
{"learn":[0.2189316379],"iteration":766,"passed_time":5.450395944,"remaining_time":1.655726538},
{"learn":[0.2187526644],"iteration":767,"passed_time":5.457755528,"remaining_time":1.648696982},
{"learn":[0.2187459997],"iteration":768,"passed_time":5.464233708,"remaining_time":1.641401803},
{"learn":[0.2186044181],"iteration":769,"passed_time":5.471596454,"remaining_time":1.634372967},
{"learn":[0.2184848186],"iteration":770,"passed_time":5.478258178,"remaining_time":1.627135049},
{"learn":[0.2183885969],"iteration":771,"passed_time":5.486468302,"remaining_time":1.620355924},
{"learn":[0.2183219187],"iteration":772,"passed_time":5.493425136,"remaining_time":1.613205053},
{"learn":[0.2181939762],"iteration":773,"passed_time":5.501815862,"remaining_time":1.606473366},
{"learn":[0.2181157942],"iteration":774,"passed_time":5.508963168,"remaining_time":1.599376403},
{"learn":[0.2181055224],"iteration":775,"passed_time":5.516776726,"remaining_time":1.592471632},
{"learn":[0.2179594944],"iteration":776,"passed_time":5.523594173,"remaining_time":1.585278636},
{"learn":[0.2179098472],"iteration":777,"passed_time":5.53230775,"remaining_time":1.578627661},
{"learn":[0.2176950096],"iteration":778,"passed_time":5.538966381,"remaining_time":1.571388409},
{"learn":[0.2175599026],"iteration":779,"passed_time":5.545952853,"remaining_time":1.564243113},
{"learn":[0.2174307575],"iteration":780,"passed_time":5.554325678,"remaining_time":1.55748697},
{"learn":[0.2173587404],"iteration":781,"passed_time":5.561031217,"remaining_time":1.550261899},
{"learn":[0.2171688049],"iteration":782,"passed_time":5.568111725,"remaining_time":1.543142075},
{"learn":[0.2170926338],"iteration":783,"passed_time":5.574788258,"remaining_time":1.535911051},
{"learn":[0.2169921731],"iteration":784,"passed_time":5.583848381,"remaining_time":1.52933427},
{"learn":[0.2168713381],"iteration":785,"passed_time":5.590870295,"remaining_time":1.522196238},
{"learn":[0.2167537463],"iteration":786,"passed_time":5.599084907,"remaining_time":1.515381303},
{"learn":[0.2166352643],"iteration":787,"passed_time":5.605378208,"remaining_time":1.508045914},
{"learn":[0.216627339],"iteration":788,"passed_time":5.611933345,"remaining_time":1.500783189},
{"learn":[0.216373326],"iteration":789,"passed_time":5.619828219,"remaining_time":1.493878387},
{"learn":[0.2163026454],"iteration":790,"passed_time":5.626352965,"remaining_time":1.486609064},
{"learn":[0.2161284927],"iteration":791,"passed_time":5.634231876,"remaining_time":1.47969726},
{"learn":[0.2160671547],"iteration":792,"passed_time":5.64077111,"remaining_time":1.472433316},
{"learn":[0.2160508213],"iteration":793,"passed_time":5.647307091,"remaining_time":1.465170353},
{"learn":[0.2159856937],"iteration":794,"passed_time":5.654436514,"remaining_time":1.458062246},
{"learn":[0.215874587],"iteration":795,"passed_time":5.661590235,"remaining_time":1.450960312},
{"learn":[0.2158289395],"iteration":796,"passed_time":5.670017759,"remaining_time":1.444182691},
{"learn":[0.2158243611],"iteration":797,"passed_time":5.676210859,"remaining_time":1.43683533},
{"learn":[0.2157241364],"iteration":798,"passed_time":5.684913964,"remaining_time":1.430122286},
{"learn":[0.2155141474],"iteration":799,"passed_time":5.691888368,"remaining_time":1.422972092},
{"learn":[0.2153968812],"iteration":800,"passed_time":5.69972766,"remaining_time":1.416037209},
{"learn":[0.2153039935],"iteration":801,"passed_time":5.706443801,"remaining_time":1.408822784},
{"learn":[0.2152537098],"iteration":802,"passed_time":5.713596518,"remaining_time":1.401716705},
{"learn":[0.215217984],"iteration":803,"passed_time":5.720734797,"remaining_time":1.39460699},
{"learn":[0.2151434316],"iteration":804,"passed_time":5.728123206,"remaining_time":1.387557795},
{"learn":[0.2149455212],"iteration":805,"passed_time":5.736333902,"remaining_time":1.380705679},
{"learn":[0.2148342073],"iteration":806,"passed_time":5.743300555,"remaining_time":1.373552673},
{"learn":[0.214808449],"iteration":807,"passed_time":5.751053893,"remaining_time":1.366587064},
{"learn":[0.2147742181],"iteration":808,"passed_time":5.757613489,"remaining_time":1.359337672},
{"learn":[0.2146948682],"iteration":809,"passed_time":5.765408664,"remaining_time":1.35237981},
{"learn":[0.2145554373],"iteration":810,"passed_time":5.77246866,"remaining_time":1.345248553},
{"learn":[0.2144169427],"iteration":811,"passed_time":5.778956479,"remaining_time":1.337984998},
{"learn":[0.2143321357],"iteration":812,"passed_time":5.785686626,"remaining_time":1.330779089},
{"learn":[0.2142396122],"iteration":813,"passed_time":5.79200562,"remaining_time":1.3234804},
{"learn":[0.2141776374],"iteration":814,"passed_time":5.798373187,"remaining_time":1.316195141},
{"learn":[0.2139659568],"iteration":815,"passed_time":5.805383093,"remaining_time":1.309056972},
{"learn":[0.2137975207],"iteration":816,"passed_time":5.811982709,"remaining_time":1.301827216},
{"learn":[0.2136049039],"iteration":817,"passed_time":5.81937175,"remaining_time":1.294774644},
{"learn":[0.2134432017],"iteration":818,"passed_time":5.826980902,"remaining_time":1.287769894},
{"learn":[0.2134287514],"iteration":819,"passed_time":5.834886388,"remaining_time":1.280828719},
{"learn":[0.2132974601],"iteration":820,"passed_time":5.841980049,"remaining_time":1.273708196},
{"learn":[0.2132013921],"iteration":821,"passed_time":5.850251338,"remaining_time":1.266842747},
{"learn":[0.2130611596],"iteration":822,"passed_time":5.856368856,"remaining_time":1.259510677},
{"learn":[0.213000292],"iteration":823,"passed_time":5.864636631,"remaining_time":1.252640834},
{"learn":[0.2127957054],"iteration":824,"passed_time":5.871491316,"remaining_time":1.245467855},
{"learn":[0.2127001098],"iteration":825,"passed_time":5.878472708,"remaining_time":1.238322338},
{"learn":[0.2126926746],"iteration":826,"passed_time":5.885575806,"remaining_time":1.231202678},
{"learn":[0.212536917],"iteration":827,"passed_time":5.892749015,"remaining_time":1.224097621},
{"learn":[0.2124212805],"iteration":828,"passed_time":5.901413887,"remaining_time":1.21730009},
{"learn":[0.2123041365],"iteration":829,"passed_time":5.908077519,"remaining_time":1.210088166},
{"learn":[0.2122008969],"iteration":830,"passed_time":5.916798134,"remaining_time":1.20329589},
{"learn":[0.2121459316],"iteration":831,"passed_time":5.924294605,"remaining_time":1.196251795},
{"learn":[0.2120264574],"iteration":832,"passed_time":5.933083513,"remaining_time":1.189465722},
{"learn":[0.2118461077],"iteration":833,"passed_time":5.940266963,"remaining_time":1.182355295},
{"learn":[0.2117116144],"iteration":834,"passed_time":5.949761994,"remaining_time":1.175701472},
{"learn":[0.2116553496],"iteration":835,"passed_time":5.957535744,"remaining_time":1.168703184},
{"learn":[0.2116453009],"iteration":836,"passed_time":5.966125637,"remaining_time":1.161861982},
{"learn":[0.2114972429],"iteration":837,"passed_time":5.974634797,"remaining_time":1.155000999},
{"learn":[0.2113427301],"iteration":838,"passed_time":5.98342005,"remaining_time":1.148189068},
{"learn":[0.2112800804],"iteration":839,"passed_time":5.992174561,"remaining_time":1.141366583},
{"learn":[0.2112701173],"iteration":840,"passed_time":6.005869564,"remaining_time":1.135473556},
{"learn":[0.2110317041],"iteration":841,"passed_time":6.018344138,"remaining_time":1.129332985},
{"learn":[0.2108689721],"iteration":842,"passed_time":6.026362194,"remaining_time":1.122347407},
{"learn":[0.2107344196],"iteration":843,"passed_time":6.035397046,"remaining_time":1.115547321},
{"learn":[0.2105563723],"iteration":844,"passed_time":6.044579367,"remaining_time":1.108768996},
{"learn":[0.2104788012],"iteration":845,"passed_time":6.057317906,"remaining_time":1.102632338},
{"learn":[0.2104179922],"iteration":846,"passed_time":6.065151856,"remaining_time":1.095594137},
{"learn":[0.210297451],"iteration":847,"passed_time":6.073906448,"remaining_time":1.08871908},
{"learn":[0.2101824652],"iteration":848,"passed_time":6.080900209,"remaining_time":1.081526421},
{"learn":[0.2100949083],"iteration":849,"passed_time":6.091061253,"remaining_time":1.074893162},
{"learn":[0.2099739894],"iteration":850,"passed_time":6.099706005,"remaining_time":1.067986128},
{"learn":[0.2098314271],"iteration":851,"passed_time":6.108280757,"remaining_time":1.061062855},
{"learn":[0.209759057],"iteration":852,"passed_time":6.116684345,"remaining_time":1.054106212},
{"learn":[0.2096008006],"iteration":853,"passed_time":6.125708122,"remaining_time":1.047252208},
{"learn":[0.2095534003],"iteration":854,"passed_time":6.134151208,"remaining_time":1.040294649},
{"learn":[0.2095310188],"iteration":855,"passed_time":6.142432868,"remaining_time":1.033306464},
{"learn":[0.2094418215],"iteration":856,"passed_time":6.151724155,"remaining_time":1.026483727},
{"learn":[0.2093652291],"iteration":857,"passed_time":6.160819669,"remaining_time":1.019622836},
{"learn":[0.209221012],"iteration":858,"passed_time":6.170565262,"remaining_time":1.012863448},
{"learn":[0.2091468566],"iteration":859,"passed_time":6.181253093,"remaining_time":1.006250503},
{"learn":[0.209067349],"iteration":860,"passed_time":6.188850296,"remaining_time":0.9991291419},
{"learn":[0.2089724632],"iteration":861,"passed_time":6.196694387,"remaining_time":0.9920462012},
{"learn":[0.20882359],"iteration":862,"passed_time":6.205302463,"remaining_time":0.985082778},
{"learn":[0.2087865014],"iteration":863,"passed_time":6.213975086,"remaining_time":0.978125708},
{"learn":[0.2087255072],"iteration":864,"passed_time":6.222741906,"remaining_time":0.9711793726},
{"learn":[0.2085423562],"iteration":865,"passed_time":6.232537268,"remaining_time":0.9643879838},
{"learn":[0.2083401002],"iteration":866,"passed_time":6.241631467,"remaining_time":0.9574821051},
{"learn":[0.20817701],"iteration":867,"passed_time":6.250671901,"remaining_time":0.950563008},
{"learn":[0.208170193],"iteration":868,"passed_time":6.25909084,"remaining_time":0.9435453395},
{"learn":[0.2080534758],"iteration":869,"passed_time":6.268980309,"remaining_time":0.936744184},
{"learn":[0.2078924519],"iteration":870,"passed_time":6.279362537,"remaining_time":0.9300089177},
{"learn":[0.2078205246],"iteration":871,"passed_time":6.287062441,"remaining_time":0.922871551},
{"learn":[0.2077441244],"iteration":872,"passed_time":6.295091612,"remaining_time":0.9157807958},
{"learn":[0.2076538741],"iteration":873,"passed_time":6.304692286,"remaining_time":0.9089144486},
{"learn":[0.2074234426],"iteration":874,"passed_time":6.312687511,"remaining_time":0.9018125016},
{"learn":[0.2072704535],"iteration":875,"passed_time":6.321443388,"remaining_time":0.8948161873},
{"learn":[0.2071298466],"iteration":876,"passed_time":6.331188649,"remaining_time":0.8879546224},
{"learn":[0.2070370022],"iteration":877,"passed_time":6.339189668,"remaining_time":0.8808441224},
{"learn":[0.2068949591],"iteration":878,"passed_time":6.348830783,"remaining_time":0.873957366},
{"learn":[0.2067896453],"iteration":879,"passed_time":6.356467284,"remaining_time":0.8667909933},
{"learn":[0.2066826248],"iteration":880,"passed_time":6.367758055,"remaining_time":0.8601171493},
{"learn":[0.2066279409],"iteration":881,"passed_time":6.375732597,"remaining_time":0.8529891684},
{"learn":[0.2065257513],"iteration":882,"passed_time":6.384658835,"remaining_time":0.8459853722},
{"learn":[0.2063756029],"iteration":883,"passed_time":6.392643929,"remaining_time":0.8388537283},
{"learn":[0.2062183404],"iteration":884,"passed_time":6.400765058,"remaining_time":0.8317378324},
{"learn":[0.2061172105],"iteration":885,"passed_time":6.407790958,"remaining_time":0.8244787462},
{"learn":[0.2060661992],"iteration":886,"passed_time":6.416149435,"remaining_time":0.8173899506},
{"learn":[0.2059718031],"iteration":887,"passed_time":6.423796308,"remaining_time":0.8102085433},
{"learn":[0.2058859168],"iteration":888,"passed_time":6.432430568,"remaining_time":0.8031493734},
{"learn":[0.205744538],"iteration":889,"passed_time":6.439632782,"remaining_time":0.7959096697},
{"learn":[0.2055961925],"iteration":890,"passed_time":6.447741752,"remaining_time":0.7887809775},
{"learn":[0.2055924044],"iteration":891,"passed_time":6.454925252,"remaining_time":0.781538035},
{"learn":[0.2054612927],"iteration":892,"passed_time":6.464605062,"remaining_time":0.7745943355},
{"learn":[0.2053640519],"iteration":893,"passed_time":6.471397167,"remaining_time":0.767302125},
{"learn":[0.205317817],"iteration":894,"passed_time":6.48028468,"remaining_time":0.7602568619},
{"learn":[0.2052271472],"iteration":895,"passed_time":6.487788149,"remaining_time":0.7530468387},
{"learn":[0.2050585324],"iteration":896,"passed_time":6.495793314,"remaining_time":0.7458937696},
{"learn":[0.2049404071],"iteration":897,"passed_time":6.502952205,"remaining_time":0.7386426781},
{"learn":[0.204886412],"iteration":898,"passed_time":6.510118346,"remaining_time":0.7313926061},
{"learn":[0.2047686807],"iteration":899,"passed_time":6.517519546,"remaining_time":0.7241688384},
{"learn":[0.204717115],"iteration":900,"passed_time":6.525535755,"remaining_time":0.7170122527},
{"learn":[0.2047107403],"iteration":901,"passed_time":6.534478799,"remaining_time":0.7099544594},
{"learn":[0.2047045841],"iteration":902,"passed_time":6.54094707,"remaining_time":0.7026266509},
{"learn":[0.2046559974],"iteration":903,"passed_time":6.548616924,"remaining_time":0.6954283459},
{"learn":[0.2045495129],"iteration":904,"passed_time":6.55618703,"remaining_time":0.688218528},
{"learn":[0.2045197823],"iteration":905,"passed_time":6.564534985,"remaining_time":0.6810886187},
{"learn":[0.204415434],"iteration":906,"passed_time":6.571103797,"remaining_time":0.6737735977},
{"learn":[0.2044118588],"iteration":907,"passed_time":6.57818544,"remaining_time":0.6665121811},
{"learn":[0.2043628829],"iteration":908,"passed_time":6.585433869,"remaining_time":0.6592678571},
{"learn":[0.2043027185],"iteration":909,"passed_time":6.592865873,"remaining_time":0.6520416797},
{"learn":[0.204271091],"iteration":910,"passed_time":6.600234764,"remaining_time":0.6448088847},
{"learn":[0.2040726082],"iteration":911,"passed_time":6.607235824,"remaining_time":0.6375402988},
{"learn":[0.2039574506],"iteration":912,"passed_time":6.614807436,"remaining_time":0.6303266669},
{"learn":[0.203793928],"iteration":913,"passed_time":6.622008807,"remaining_time":0.6230774151},
{"learn":[0.2036358856],"iteration":914,"passed_time":6.629455951,"remaining_time":0.6158510993},
{"learn":[0.2034721161],"iteration":915,"passed_time":6.635980908,"remaining_time":0.6085397339},
{"learn":[0.2033290088],"iteration":916,"passed_time":6.645319283,"remaining_time":0.6014847333},
{"learn":[0.2032689542],"iteration":917,"passed_time":6.651975103,"remaining_time":0.5941851399},
{"learn":[0.2031794905],"iteration":918,"passed_time":6.659451845,"remaining_time":0.586959303},
{"learn":[0.2030019209],"iteration":919,"passed_time":6.666580677,"remaining_time":0.5797026675},
{"learn":[0.2029016452],"iteration":920,"passed_time":6.673355954,"remaining_time":0.5724159831},
{"learn":[0.2027536777],"iteration":921,"passed_time":6.680623962,"remaining_time":0.5651720922},
{"learn":[0.2026455752],"iteration":922,"passed_time":6.687751157,"remaining_time":0.557916402},
{"learn":[0.2025992647],"iteration":923,"passed_time":6.695634475,"remaining_time":0.5507231819},
{"learn":[0.2024995853],"iteration":924,"passed_time":6.701891279,"remaining_time":0.5433965902},
{"learn":[0.2024551291],"iteration":925,"passed_time":6.710388903,"remaining_time":0.536251381},
{"learn":[0.2023348464],"iteration":926,"passed_time":6.717090717,"remaining_time":0.5289618364},
{"learn":[0.2022612334],"iteration":927,"passed_time":6.724103244,"remaining_time":0.5216976654},
{"learn":[0.2022476837],"iteration":928,"passed_time":6.730935188,"remaining_time":0.514420235},
{"learn":[0.2021386106],"iteration":929,"passed_time":6.738231067,"remaining_time":0.5071786825},
{"learn":[0.2020177544],"iteration":930,"passed_time":6.745572328,"remaining_time":0.4999403766},
{"learn":[0.2018696068],"iteration":931,"passed_time":6.752918458,"remaining_time":0.4927022051},
{"learn":[0.2018472979],"iteration":932,"passed_time":6.761119546,"remaining_time":0.4855251978},
{"learn":[0.2016718467],"iteration":933,"passed_time":6.768388186,"remaining_time":0.4782801074},
{"learn":[0.201580671],"iteration":934,"passed_time":6.775794226,"remaining_time":0.4710445184},
{"learn":[0.2015429873],"iteration":935,"passed_time":6.782150819,"remaining_time":0.4637368082},
{"learn":[0.2014370501],"iteration":936,"passed_time":6.789164681,"remaining_time":0.4564753201},
{"learn":[0.2013472264],"iteration":937,"passed_time":6.796188703,"remaining_time":0.4492150316},
{"learn":[0.201257572],"iteration":938,"passed_time":6.802736893,"remaining_time":0.4419243349},
{"learn":[0.201117948],"iteration":939,"passed_time":6.811538522,"remaining_time":0.4347790546},
{"learn":[0.2010347595],"iteration":940,"passed_time":6.818198238,"remaining_time":0.4274959575},
{"learn":[0.2008342004],"iteration":941,"passed_time":6.826324236,"remaining_time":0.4203044646},
{"learn":[0.2007986995],"iteration":942,"passed_time":6.833383479,"remaining_time":0.4130465093},
{"learn":[0.2007032181],"iteration":943,"passed_time":6.84196551,"remaining_time":0.4058793099},
{"learn":[0.2005294411],"iteration":944,"passed_time":6.848910155,"remaining_time":0.3986138186},
{"learn":[0.200478948],"iteration":945,"passed_time":6.85629258,"remaining_time":0.3913739951},
{"learn":[0.2003988278],"iteration":946,"passed_time":6.863815246,"remaining_time":0.3841417192},
{"learn":[0.2003864513],"iteration":947,"passed_time":6.870155254,"remaining_time":0.3768439591},
{"learn":[0.2003606644],"iteration":948,"passed_time":6.877937819,"remaining_time":0.3696257416},
{"learn":[0.2003302692],"iteration":949,"passed_time":6.885411208,"remaining_time":0.3623900636},
{"learn":[0.200324058],"iteration":950,"passed_time":6.893343672,"remaining_time":0.3551775393},
{"learn":[0.2002260802],"iteration":951,"passed_time":6.899810215,"remaining_time":0.3478895907},
{"learn":[0.2001805133],"iteration":952,"passed_time":6.907195602,"remaining_time":0.3406486813},
{"learn":[0.200133644],"iteration":953,"passed_time":6.914744483,"remaining_time":0.3334153524},
{"learn":[0.2001279085],"iteration":954,"passed_time":6.920540927,"remaining_time":0.3260987871},
{"learn":[0.2000103529],"iteration":955,"passed_time":6.928647548,"remaining_time":0.3188917281},
{"learn":[0.1999920868],"iteration":956,"passed_time":6.93540653,"remaining_time":0.311622237},
{"learn":[0.1999265599],"iteration":957,"passed_time":6.944318501,"remaining_time":0.3044482015},
{"learn":[0.1997427258],"iteration":958,"passed_time":6.951346609,"remaining_time":0.297190001},
{"learn":[0.1995862988],"iteration":959,"passed_time":6.959930638,"remaining_time":0.2899971099},
{"learn":[0.1995361834],"iteration":960,"passed_time":6.966748597,"remaining_time":0.2827296517},
{"learn":[0.1995121798],"iteration":961,"passed_time":6.975365186,"remaining_time":0.2755341758},
{"learn":[0.1994756715],"iteration":962,"passed_time":6.982553294,"remaining_time":0.2682808639},
{"learn":[0.1993105995],"iteration":963,"passed_time":6.990341974,"remaining_time":0.2610501152},
{"learn":[0.1991496857],"iteration":964,"passed_time":6.997364962,"remaining_time":0.253790439},
{"learn":[0.1990419037],"iteration":965,"passed_time":7.00396778,"remaining_time":0.2465164643},
{"learn":[0.198998855],"iteration":966,"passed_time":7.011768628,"remaining_time":0.2392847619},
{"learn":[0.1989477979],"iteration":967,"passed_time":7.018692209,"remaining_time":0.2320228829},
{"learn":[0.1988985],"iteration":968,"passed_time":7.027194813,"remaining_time":0.2248122179},
{"learn":[0.1988657285],"iteration":969,"passed_time":7.034052199,"remaining_time":0.2175480061},
{"learn":[0.1988442038],"iteration":970,"passed_time":7.041588328,"remaining_time":0.2103049037},
{"learn":[0.1988399678],"iteration":971,"passed_time":7.047844601,"remaining_time":0.2030243301},
{"learn":[0.1987218679],"iteration":972,"passed_time":7.05647865,"remaining_time":0.1958118433},
{"learn":[0.1986253448],"iteration":973,"passed_time":7.063414992,"remaining_time":0.1885511189},
{"learn":[0.1985141834],"iteration":974,"passed_time":7.070522598,"remaining_time":0.1812954512},
{"learn":[0.1984765061],"iteration":975,"passed_time":7.07812185,"remaining_time":0.1740521766},
{"learn":[0.1983611438],"iteration":976,"passed_time":7.085909556,"remaining_time":0.1668126098},
{"learn":[0.1983577693],"iteration":977,"passed_time":7.093327744,"remaining_time":0.1595636098},
{"learn":[0.1982772023],"iteration":978,"passed_time":7.100241034,"remaining_time":0.1523034338},
{"learn":[0.1981447719],"iteration":979,"passed_time":7.108364732,"remaining_time":0.145068668},
{"learn":[0.1981269366],"iteration":980,"passed_time":7.115419959,"remaining_time":0.1378113957},
{"learn":[0.1980282716],"iteration":981,"passed_time":7.123003408,"remaining_time":0.1305642173},
{"learn":[0.1979053844],"iteration":982,"passed_time":7.130226757,"remaining_time":0.123310127},
{"learn":[0.19775024],"iteration":983,"passed_time":7.136819586,"remaining_time":0.1160458469},
{"learn":[0.1977095992],"iteration":984,"passed_time":7.14470444,"remaining_time":0.1088026057},
{"learn":[0.1976826897],"iteration":985,"passed_time":7.151138905,"remaining_time":0.1015374692},
{"learn":[0.1975480296],"iteration":986,"passed_time":7.158883428,"remaining_time":0.09429127108},
{"learn":[0.1974804656],"iteration":987,"passed_time":7.165907691,"remaining_time":0.08703531608},
{"learn":[0.1973466967],"iteration":988,"passed_time":7.174643477,"remaining_time":0.07979886577},
{"learn":[0.1972511057],"iteration":989,"passed_time":7.181677499,"remaining_time":0.07254219696},
{"learn":[0.1971718406],"iteration":990,"passed_time":7.189018468,"remaining_time":0.0652887651},
{"learn":[0.1970925858],"iteration":991,"passed_time":7.196241737,"remaining_time":0.05803420756},
{"learn":[0.1970152242],"iteration":992,"passed_time":7.203069404,"remaining_time":0.0507769243},
{"learn":[0.1970121689],"iteration":993,"passed_time":7.209716058,"remaining_time":0.04351941282},
{"learn":[0.1969254327],"iteration":994,"passed_time":7.216739066,"remaining_time":0.03626502043},
{"learn":[0.1968101643],"iteration":995,"passed_time":7.224942162,"remaining_time":0.02901583198},
{"learn":[0.1967832761],"iteration":996,"passed_time":7.231751336,"remaining_time":0.02176053561},
{"learn":[0.196688849],"iteration":997,"passed_time":7.23981393,"remaining_time":0.01450864515},
{"learn":[0.196638049],"iteration":998,"passed_time":7.247033615,"remaining_time":0.007254287902},
{"learn":[0.196536153],"iteration":999,"passed_time":7.255655104,"remaining_time":0}
]}